Workbook

Sheet Revenue-Cost_2024
B1: Daily Report - Balance Calculation Operation Cost
B2: Project | C2: : | D2: REVENUE vs OPERATION COST Tahun 2024
B3: Date | C3: : | D3: Januari - Desember 2024
B5: REVENUE & TAX
B6: Invoice Date | C6: # | D6: Detail/Description | F6: INVOICE VALUE | G6: Currency | H6: Currency Exchange | I6: INVOICE Number | J6: Client | K6: Receive Date | L6: AMOUNT RECEIVED | M6: PPn | N6: PPH (Pasal 23) | O6: Biaya transfer | P6: Remark
L7: IDR | M7: 0.11 | N7: 0.02 | Q7: con: inc.PPN11%
B8: 11-Jan-24 | C8: 1 | D8: ALFA Service PDP-075 Pertamina Zona#4 | F8: 354210000 | G8: IDR | H8: 1 | I8: INV017 | J8: SI Jak | K8: 28-Feb-24 | L8: 347125800 | M8: 38963100 | N8: 7084200 | O8: 0 | P8: Pemungut
B9: 10-Jan-24 | C9: 2 | D9: Revenue data procesing MTD_Tomori | F9: 150000000 | G9: IDR | H9: 1 | I9: INV015 | J9: TGE | K9: 17-Apr-24 | L9: 166500000 | M9: 16500000 | N9: 3000000 | O9: 0
B10: 11-Jan-24 | C10: 3 | D10: ALFA Service PDS-01ST Pertamina Zona#4 | F10: 354210000 | G10: IDR | H10: 1 | I10: INV019 | J10: SI Jak | K10: 13-May-24 | L10: 347125800 | M10: 38963100 | N10: 7084200 | O10: 0 | P10: Pemungut
B11: 11-Jan-24 | C11: 4 | D11: ALFA Service JRK-254 Pertamina Zona#4 | F11: 354210000 | G11: IDR | H11: 1 | I11: INV018 | J11: SI Jak | K11: 10-Jun-24 | L11: 347125800 | M11: 38963100 | N11: 7084200 | O11: 0 | P11: Pemungut
B12: 03-Jun-24 | C12: 5 | D12: ALFA Service TLJ-58 Pertamina Zona#4 | F12: 354210000 | G12: IDR | H12: 1 | I12: INV020 | J12: SI Jak | K12: 24-Jul-24 | L12: 347125800 | M12: 38963100 | N12: 7084200 | O12: 0 | P12: Pemungut
B13: 04-Jun-24 | C13: 6 | D13: ALFA Service JRK-193 Pertamina Zona#4 | F13: 354210000 | G13: IDR | H13: 1 | I13: INV021 | J13: SI Jak | K13: 12-Aug-24 | L13: 347125800 | M13: 38963100 | N13: 7084200 | O13: 0 | P13: Pemungut
B14: 04-Sep-24 | C14: 7 | D14: Revenue Repair Electric Assisted Stimulation Machine (no 23) | F14: 89000000 | G14: IDR | H14: 1 | I14: INV023 | J14: LBU | K14: 18-Sep-24 | L14: 96920000 | M14: 9790000 | N14: 1780000 | O14: 0
B15: 02-Sep-24 | C15: 8 | D15: ALFA Service JRK-163 Pertamina Zona#4 | F15: 354210000 | G15: IDR | H15: 1 | I15: INV022 | J15: SI Jak | K15: 10-Oct-24 | L15: 347125800 | M15: 38963100 | N15: 7084200 | O15: 0 | P15: Pemungut
B16: 11-Oct-24 | C16: 9 | D16: Revenue Project TIS (no 28 ) | F16: 819200000 | G16: IDR | H16: 1 | I16: INV028 | J16: Barikin Sakti | K16: 14-Oct-24 | L16: 892928000 | M16: 90112000 | N16: 16384000 | O16: 0
B17: 07-Oct-24 | C17: 10 | D17: ALFA Service JRK-095 Pertamina Zona#4 | F17: 354210000 | G17: IDR | H17: 1 | I17: INV027 | J17: SI Jak | K17: 11-Nov-24 | L17: 347125800 | M17: 38963100 | N17: 7084200 | O17: 0 | P17: Pemungut
B18: 04-Oct-24 | C18: 11 | D18: ALFA Service TGB-033 Pertamina Cirebon | F18: 290000000 | G18: IDR | H18: 1 | I18: INV024 | J18: Elnusa | K18: 20-Dec-24 | L18: 284197100 | M18: 31900000 | N18: 5800000 | O18: 2900 | P18: Pemungut
B19: 04-Oct-24 | C19: 12 | D19: MFC Service TGB-033 Pertamina Cirebon | F19: 280000000 | G19: IDR | H19: 1 | I19: INV025 | J19: Elnusa | K19: 27-Dec-24 | L19: 412577100 | M19: 30800000 | N19: 5600000 | O19: 2900 | P19: Pemungut
B20: 04-Oct-24 | C20: 13 | D20: PLT Service TGB-033 Pertamina Cirebon | F20: 141000000 | G20: IDR | H20: 1 | I20: INV026 | J20: Elnusa | K20: 27-Dec-24 | L20: 0 | M20: 15510000 | N20: 2820000 | O20: 0
B21: 31-Dec-24 | C21: 14 | D21: Bunga Bank 2024 | F21: 6925425 | G21: IDR | H21: 1 | L21: 6925425 | M21: 0 | N21: 0 | O21: 0
B22: REVENUE (IDR) | F22: =SUM(F8:F21) | L22: =SUM(L8:L21) | M22: =SUM(M8:M21) | N22: =SUM(N8:N21) | O22: =SUM(O8:O21)
B24: PAJAK PENGELUARAN
B25: Date | C25: # | D25: Detail/Description | F25: Transaction Value | G25: Currency | H25: Currency Exchange | I25: PPN | K25: PPh (pasal 21) | M25: PPh (pasal 23) | O25: PPh (pasal 26)
I26: Transaction | J26: PPN | K26: Transaction | L26: PPh - 21 | M26: Transaction | N26: PPh - 23 | O26: Transaction | P26: PPh - 26
B27: 11-Jan-24 | C27: 1 | D27: Tax PPN 11% (Project TGE MEPI Rimau Pembayaran Ke-2) | F27: 33836000 | G27: IDR | H27: 1 | I27: 33836000 | J27: 33836000
B28: 29-Feb-24 | C28: 2 | D28: Tax PPN 11% (Project TGE MEPI Tomori) | F28: 16500000 | G28: IDR | H28: 1 | I28: 16500000 | J28: 16500000
B29: 11-Sep-24 | C29: 3 | D29: Pinalty Telat bayar pajak PP21 Sewa tool ALFA 2023 | F29: 25439666 | G29: IDR | H29: 1 | K29: 25439666 | L29: 25439666
B30: 11-Sep-24 | C30: 4 | D30: Tax PPN 11% pajak Inv-007 tahun 2023 sarulla project - Sibat | F30: 96126126 | G30: IDR | H30: 1 | I30: 96126126 | J30: 97126126
B31: 02-Oct-24 | C31: 5 | D31: Tax PPN 11% (Perbaikan Repair Electric Assisted Stimulation Machine) | F31: 9790000 | G31: IDR | H31: 1 | I31: 9790000 | J31: 9790000
B32: 24-Oct-24 | C32: 6 | D32: Penalty telat bayar pajak PPN project sarulla_INV-007_under Sibat | F32: 17716045 | G32: IDR | H32: 1
B33: 28-Oct-24 | C33: 7 | D33: Pemindahbukan dari double bayar (29 des 2023) utk PPN Inv-028 | F33: 33836000 | G33: IDR | H33: 1 | I33: 33836000 | J33: 33836000
B34: 11-Nov-24 | C34: 8 | D34: Kekurangan pajak PPn Inv-028 (barikikn Sakti)(1/3 nya dari PBK pajak) | F34: 56276000 | G34: IDR | H34: 1 | I34: 56276000 | J34: 56276000
B35: 11-Nov-24 | C35: 9 | D35: Kekurangan pajak final PPH 23 keuntungan perusahaan tahun 2023 | F35: 1726469 | G35: IDR | H35: 1 | M35: 1726469 | N35: 1726469
B36: PENERIMAAN NEGARA (TAX) (IDR) | I36: PPN | J36: =SUM(J27:J35) | K36: PPh | L36: =SUM(L27:L35) | M36: PPh | N36: =SUM(N27:N35) | O36: PPh | P36: =SUM(P27:P35) | Q36: -
B38: PENGELUARAN
B39: Date | C39: # | D39: Activity | E39: Source | F39: Jumlah | G39: Currency | H39: urrency Exchange | I39: Biaya Research (R&D) | J39: Biaya Operasi | K39: diofavian | L39: Biaya Sewa Peralatan | M39: Biaya Interpretasi Log Data | N39: Administrasi | O39: Pembelian Barang | P39: Sewa Kantor | Q39: Kesehatan | R39: Bisnis Dev | S39: asdasd | T39: makanan jepang | U39: aaaaa | V39: bbbbb | W39: asdsad | X39: dfgdfgdfgd | Y39: 12312
D40: Biaya Bank
B41: 31-Dec-24 | C41: 1 | D41: Total Biaya Transaksi Bank selama 1 tahun | E41: - | F41: 1998587 | G41: IDR | H41: 1 | I41: 1998587
D42: Biaya Interpretasi Log Data
B43: 01-May-24 | C43: 2 | D43: Data proccesing MTD 4 well, project Tomori-Alan | E43: BCA | F43: 122625000 | G43: IDR | H43: 1 | M43: 122625000
B44: 21-Aug-24 | C44: 3 | D44: Data proccesing TGB-33 DAN TIS (RBG-3b)-Alan | E44: BCA | F44: 101120000 | G44: IDR | H44: 1 | M44: 101120000
B45: 24-Oct-24 | C45: 4 | D45: Data Processing 8 Well Alan Project SIJAK | E45: BRI | F45: 144000000 | G45: IDR | H45: 1 | M45: 144000000
D46: Biaya Operasi
B47: 13-Jan-24 | C47: 5 | D47: Sales cost 4 Well Integrity Pertamina Z.4 | E47: BRI | F47: 77672400 | G47: IDR | H47: 1 | J47: 77672400
B48: 01-Feb-24 | C48: 6 | D48: Gaji Januari 2024 _Yufitri | E48: BCA | F48: 2500000 | G48: IDR | H48: 1 | J48: 2500000
B49: 05-Mar-24 | C49: 7 | D49: Gaji Februari 2024 + raple gaji Januari 2024_Yufitri | E49: BCA | F49: 3500000 | G49: IDR | H49: 1 | J49: 3500000
B50: 28-Mar-24 | C50: 8 | D50: Gaji Maret 2024_Yufitri | E50: BCA | F50: 3000000 | G50: IDR | H50: 1 | J50: 3000000
B51: 06-Apr-24 | C51: 9 | D51: THR 2024_Yufitri | E51: BCA | F51: 3000000 | G51: IDR | H51: 1 | J51: 3000000
B52: 04-May-24 | C52: 10 | D52: Gaji April_Yufitri | E52: BCA | F52: 3000000 | G52: IDR | H52: 1 | J52: 3000000
B53: 10-May-24 | C53: 11 | D53: Aro Energy | Moving slickline dari Duri (Toni Supriadi) ke Sungai lilin | E53: BCA | F53: 18000000 | G53: IDR | H53: 1 | J53: 18000000
B54: 03-Jun-24 | C54: 12 | D54: PT Laka Indonesia | Wastafel for WIKA Anantara Ubud Bali | E54: BCA | F54: 300000000 | G54: IDR | H54: 1 | J54: 300000000
B55: 03-Jun-24 | C55: 13 | D55: Gaji Mei_Yufitri | E55: BCA | F55: 3000000 | G55: IDR | H55: 1 | J55: 3000000
B56: 30-Jun-24 | C56: 14 | D56: Gaji Juni 2024_Yufitri | E56: BCA | F56: 3000000 | G56: IDR | H56: 1 | J56: 3000000
B57: 05-Jul-24 | C57: 15 | D57: Repair ESOR panel & Fabricate dummy test load, Payment#2 | E57: BRI | F57: 25000000 | G57: IDR | H57: 1 | J57: 25000000
B58: 07-Jul-24 | C58: 16 | D58: PT Laka Indonesia | Wastafel for WIKA Anantara Ubud Bali | E58: BCA | F58: 25000000 | G58: IDR | H58: 1 | J58: 25000000
... B69: 25-Dec-24 | C69: 27 | D69: Gaji Desember 2024 + Bomnus akhir tahun - 4 bulan_Yufitri | E69: BCA | F69: 15000000 | G69: IDR | H69: 1 | J69: 15000000
D70: Biaya Research (R&D)
B71: 13-Mar-24 | C71: 28 | D71: Ralika Jaya Utama | Permbuatan alat Downhole Wireless Telemetry | E71: BCA | F71: 100000000 | G71: IDR | H71: 1 | I71: 100000000
B72: 06-May-24 | C72: 29 | D72: Ralika Jaya Utama | Permbuatan alat Downhole Wireless Telemetry | E72: BRI | F72: 100000000 | G72: IDR | H72: 1 | I72: 100000000
B73: 29-Jul-24 | C73: 30 | D73: Ralika Jaya Utama | Permbuatan alat injeksi listrik (EAS) | E73: BRI | F73: 100000000 | G73: IDR | H73: 1 | I73: 100000000
B74: 13-Sep-24 | C74: 31 | D74: Ralika Jaya Utama | Permbuatan alat EMR | E74: BRI | F74: 150000000 | G74: IDR | H74: 1 | I74: 150000000
B75: 05-Dec-24 | C75: 32 | D75: Ralika Jaya Utama | Permbuatan alat injeksi listrik (EAS) | E75: BRI | F75: 400000000 | G75: IDR | H75: 1 | I75: 400000000
B76: 27-Dec-24 | C76: 33 | D76: KUPA | Pembelian Mesin Retort Horizontal 500 Lt Automatic Control | E76: BCA | F76: 141500000 | G76: IDR | H76: 1 | I76: 141500000
D77: Bisnis Dev
B78: 10-Jul-24 | C78: 34 | D78: Pembelian Lisence Sonoechometer to PT Weebz Mandiri | E78: BCA | F78: 16650000 | G78: IDR | H78: 1 | R78: 16650000
B79: 15-Aug-24 | C79: 35 | D79: MUTRI | Sewa ruangan kantor BBC 2 bulan | E79: BCA | F79: 11270000 | G79: IDR | H79: 1 | R79: 11270000
B80: 04-Sep-24 | C80: 36 | D80: MUTRI | Penambahan modal biaya kerja | E80: BRI | F80: 100000000 | G80: IDR | H80: 1 | R80: 100000000
B81: 29-Nov-24 | C81: 37 | D81: MUTRI | Penambahan modal biaya kerja 3rd | E81: BRI | F81: 75000000 | G81: IDR | H81: 1 | R81: 75000000
D82: Pembelian Barang
B83: 30-Jun-24 | C83: 38 | D83: Downhole Sampling tool #1-1 GARINDO SARANA BARU | E83: BCA | F83: 39800000 | G83: IDR | H83: 1 | O83: 39800000
B84: 03-Jul-24 | C84: 39 | D84: Kekurangan (PPN ) ke PT Garindo sarana Baru (Downhole Sampling) | E84: BCA | F84: 3582000 | G84: IDR | H84: 1 | O84: 3582000
B85: 28-Jul-24 | C85: 40 | D85: Handphone Operational untuk Secretary (Yufitri) | E85: BCA | F85: 2600000 | G85: IDR | H85: 1 | O85: 2600000
B86: 15-Aug-24 | C86: 41 | D86: Downhole Sampling tool #1-2 GARINDO SARANA BARU | E86: BCA | F86: 53835000 | G86: IDR | H86: 1 | O86: 53835000
B87: 21-Sep-24 | C87: 42 | D87: Downhole Sampling tool #2 GARINDO SARANA BARU | E87: BCA | F87: 34299000 | G87: IDR | H87: 1 | O87: 34299000
B88: 04-Dec-24 | C88: 43 | D88: Payment ke UPS Biaya Import pembelian sparepart dari Pei-Genesis | E88: BRI | F88: 777246 | G88: IDR | H88: 1 | O88: 777246
D89: Rental Tool
B90: 11-Jan-24 | C90: 44 | D90: ALFA Service PDP-075 Pertamina Zona#4 - Rental Tool | E90: BCA | F90: 29640916 | G90: IDR | H90: 1 | I90: 29640916
B91: 11-Jan-24 | C91: 45 | D91: ALFA Service PDS-01ST Pertamina Zona#4 - Rental Tool | E91: BCA | F91: 29640916 | G91: IDR | H91: 1 | I91: 29640916
B92: 11-Jan-24 | C92: 46 | D92: ALFA Service JRK-254 Pertamina Zona#4 - Rental Tool | E92: BCA | F92: 29640916 | G92: IDR | H92: 1 | I92: 29640916
B93: 03-Jun-24 | C93: 47 | D93: ALFA Service TLJ-58 Pertamina Zona#4 - Rental Tool | E93: BCA | F93: 29640916 | G93: IDR | H93: 1 | I93: 29640916
B94: 04-Jun-24 | C94: 48 | D94: ALFA Service JRK-193 Pertamina Zona#4 - Rental Tool | E94: BCA | F94: 29640916 | G94: IDR | H94: 1 | I94: 29640916
B95: 02-Sep-24 | C95: 49 | D95: ALFA Service JRK-163 Pertamina Zona#4 - Rental Tool | E95: BCA | F95: 29640916 | G95: IDR | H95: 1 | I95: 29640916
B96: 04-Oct-24 | C96: 50 | D96: PLT Service TGB-033 Pertamina Cirebon - Rental Tool | E96: BCA | F96: 16165271 | G96: IDR | H96: 1 | I96: 16165271
B97: 04-Oct-24 | C97: 51 | D97: ALFA Service TGB-033 Pertamina Cirebon - Rental Tool | E97: BCA | F97: 25967616 | G97: IDR | H97: 1 | I97: 25967616
B98: 04-Oct-24 | C98: 52 | D98: MFC Service TGB-033 Pertamina Cirebon - Rental Tool | E98: BCA | F98: 32101247 | G98: IDR | H98: 1 | I98: 32101247
B99: 07-Oct-24 | C99: 53 | D99: ALFA Service JRK-095 Pertamina Zona#4 - Rental Tool | E99: BCA | F99: 29640916 | G99: IDR | H99: 1 | I99: 29640916
B100: 11-Oct-24 | C100: 54 | D100: MPLT/GR-CCL/ALFA TIS - Rental Tool | E100: BCA | F100: 74291457 | G100: IDR | H100: 1 | I100: 74291457
D101: Sewa Kantor
B102: 06-Dec-24 | C102: 55 | D102: Sewa Virtual Office 1th, 1jan25 - 31des25_BBC_ Ganesha Dwipaya B | E102: BCA | F102: 4995000 | G102: IDR | H102: 1 | P102: 4995000
D103: OPERATION COST AND OFFICE - Expenses Report
B104: Expense#1 | C104: : | D104: ALFA_ TLJ-58 (PEPZ4-Prabumulih field) SIJak- IC
D105: Biaya Operasi
B106: 07-Feb-24 | C106: 1 | D106: Airplane Ticket CGK-PLM | E106: - | F106: 1608000 | G106: IDR | H106: 1 | J106: 1608000
B107: 07-Feb-24 | C107: 2 | D107: Taxi Bintaro-CGK | E107: - | F107: 250000 | G107: IDR | H107: 1 | J107: 250000
B108: 07-Feb-24 | C108: 3 | D108: Hotel 7 Feb-8 Feb 2024 (1 days) | E108: - | F108: 200000 | G108: IDR | H108: 1 | J108: 200000
B109: 07-Feb-24 | C109: 4 | D109: Hotel Prabumulih 8 Feb- 7 Mar 2024 (1 Month) | E109: - | F109: 3300000 | G109: IDR | H109: 1 | J109: 3300000
B110: 08-Feb-24 | C110: 5 | D110: Rental Mobil Pajero 1 Hari | E110: - | F110: 900000 | G110: IDR | H110: 1 | J110: 900000
B111: 08-Feb-24 | C111: 6 | D111: Rental Mobil Pajero Sebulan | E111: - | F111: 18000000 | G111: IDR | H111: 1 | J111: 18000000
B112: 04-Mar-24 | C112: 7 | D112: Airplane Ticket PLM-CGK | E112: - | F112: 1119500 | G112: IDR | H112: 1 | J112: 1119500
B113: 04-Mar-24 | C113: 8 | D113: Taxi CGK-Bintaro | E113: - | F113: 250000 | G113: IDR | H113: 1 | J113: 250000
...

Sheet Laba rugi -2024
B3: PT. EXSPAN WIRELINE INDONESIA | G3: PT. EXSPAN WIRELINE INDONESIA
B4: LABA RUGI | TAHUN 2024 | G4: NERACA |TAHUN YANG BERAKHIR, 31 DESEMBER 2024
D6: PT. Exspan Wireline Indonesia | I6: PT. Exspan Wireline Indonesia
D7: (Rp) | I7: (Rp)
B8: PENDAPATAN | G8: AKTIVA
C9: PENDAPATAN LANGSUNG | D9: Rp | E9: =SUM('Revenue-Cost_2024'!L8:L20) | G9: AKTIVA LANCAR
C10: PENDAPATAN LAIN LAIN | D10: Rp | E10: =SUM('Revenue-Cost_2024'!L21:L21) | H10: KAS DAN SETARA KAS TAHUN SEBELUMNYA | I10: Rp | J10: 0
H11: KAS DAN SETARA KAS TAHUN LAPORAN | I11: Rp | J11: =E46-'Business Summary'!E13
B12: TOTALPENDAPATAN | D12: Rp | E12: =SUM(E9:E11) | H12: PIUTANG USAHA | I12: Rp | J12: 0
H13: PAJAK BAYAR DI MUKA (pph23) | I13: Rp | J13: 0
B14: BEBAN LANGSUNG | H14: BIAYA BAYAR DI MUKA | I14: Rp | J14: 0
C15: Biaya Operasi | D15: Rp | E15: ='Revenue-Cost_2024'!I638 | H15: PIUTANG LAIN LAIN | I15: Rp | J15: 0
C16: Biaya research (R & D) | D16: Rp | E16: ='Revenue-Cost_2024'!J638 | H16: TOTAL AKTIVA LANCAR | I16: Rp | J16: =SUM(J10:J15)
C17: BIAYA SEWA PERALATAN | D17: Rp | E17: ='Revenue-Cost_2024'!K638
C18: BIAYA Data Processing | D18: Rp | E18: ='Revenue-Cost_2024'!L638 | G18: ACTIVA TETAP
H20: INVENTARIS KANTOR | I20: Rp | J20: 0
B21: TOTAL BIAYA LANGSUNG | D21: Rp | E21: =SUM(E15:E20)
H22: TOTAL AKTIVA TETAP | I22: Rp | J22: =J20
B23: BEBAN TIDAK LANGSUNG | E23: ='Revenue-Cost_2024'!Q638
G24: ACTIVA LAIN LAIN | J24: 0
D25: Rp | J25: 0
H26: TOTAL AKTIVA LAIN LAIN | I26: Rp | J26: =SUM(J25:J25)
B27: TOTAL BIAYA TIDAK LANGSUNG | D27: Rp | E27: =SUM(E22:E26)
G28: TOTAL AKTIVA | I28: Rp | J28: =J26+J22+J16
B29: BIAYA ADMINISTRASI DAN UMUM
C30: BIAYA ADMINISTRASI | D30: Rp | E30: ='Revenue-Cost_2024'!M638 | G30: HUTANG DAN MODAL
C31: BIAYA PEMBELIAN Barang | D31: Rp | E31: ='Revenue-Cost_2024'!N638
C32: BIAYA SEWA KANTOR | D32: Rp | E32: ='Revenue-Cost_2024'!O638 | G32: HUTANG LANCAR
C33: BIAYA KESEHATAN | D33: Rp | E33: ='Revenue-Cost_2024'!P638 | H33: HUTANG USAHA | I33: Rp | J33: 0
H34: HUTANG GAJI | I34: Rp | J34: 0
B35: TOTAL BIAYA ADMINISTRASI DAN UMUM | D35: Rp | E35: =SUM(E30:E34) | H35: HUTANG PEMEGANG SAHAM | I35: Rp | J35: 0
H36: BIAYA YANG MASIH HARUS DI BAYAR | I36: Rp | J36: 0
B37: TOTAL BIAYA | D37: Rp | E37: =E35+E21+E27
H38: TOTAL HUTANG LANCAR | J38: =SUM(J33:J36)
B39: PENDAPATAN/BEBAN LAIN LAIN | D39: Rp
C40: PENDAPATAN LAINNYA | D40: Rp | E40: 0 | G40: MODAL
H41: MODAL SAHAM | I41: Rp | J41: 0
B42: LABA RUGI SEBELUM PAJAK | D42: Rp | E42: =E12-E37 | H42: LABA DI TAHAN | I42: Rp | J42: 0
H43: TOTAL LABA (RUGI) DITAHAN | I43: Rp | J43: =J28-J38-J41-J42
B44: CORPORATE TAX (PPh 29) | D44: Rp | E44: 0 | H44: TOTAL MODAL | I44: Rp | J44: =SUM(J41:J43)
B46: LABA / RUGI BERSIH | E46: =E42-E44 | G46: TOTAL HUTANG DAN MODAL | I46: Rp | J46: =J44+J38
B50: Direktur | G50: Direktur

Sheet Business Summary
B3: PT. EXSPAN WIRELINE INDONESIA
B4: BUSINESS SUMMARY | TAHUN 2024
B6: # | C6: Items | D6: Amount
B7: 1 | C7: Revenue | D7: Rp | E7: =SUM('Revenue-Cost_2024'!L8:L21)
B8: 2 | C8: Revenue Diterima (Setelah Pajak) | D8: Rp | E8: =E7-SUM('Revenue-Cost_2024'!N8:N21)
B9: 3 | C9: Biaya | D9: Rp | E9: =SUM('Revenue-Cost_2024'!I638:Q638)
B10: 4 | C10: Profit SebelumTax | D10: Rp | E10: =E7-E9
B11: 5 | C11: PPh Badan (22%*50%) | D11: Rp | E11: =E10*22%*50%
B12: 6 | C12: PPh 23 Dipotong oleh client | D12: Rp | E12: =SUM('Revenue-Cost_2024'!N8:N21)
B13: 7 | C13: Kekurangan Bayar PPh Badan | D13: Rp | E13: =E11-E12
B14: 8 | C14: Profit After Tax | D14: Rp | E14: =E10-E13
B15: 9 | C15: Deviden Dibagi | D15: Rp | E15: =E14-E16
B16: 10 | C16: Profit Ditahan | D16: Rp | E16: 33763737
B18: DEVIDEN
B19: # | C19: Nama Lengkap | E19: Amount | G19: Pajak
B20: 1 | C20: Anevril Chairulsyah | D20: Rp | E20: =IF(C20="","",ROUND($E$15/COUNTA($C$20:$C$21), 0)) | G20: Pajak 10%
B21: 2 | C21: Alan Muhadjir | D21: Rp | E21: =IF(C21="","",ROUND($E$15/COUNTA($C$20:$C$21), 0)) | G21: Pajak 10%
