Workbook

Sheet Revenue-Cost_2030
B1: Daily Report - Balance Calculation Operation Cost
B2: Project | C2: : | D2: REVENUE vs OPERATION COST Tahun 2030
B3: Date | C3: : | D3: Januari - Desember 2030
B5: REVENUE & TAX
B6: Invoice Date | C6: # | D6: Detail/Description | F6: INVOICE VALUE | G6: Currency | H6: Currency Exchange | I6: INVOICE Number | J6: Client | K6: Receive Date | L6: AMOUNT RECEIVED | M6: PPn | N6: PPH (Pasal 23) | O6: Biaya transfer | P6: Remark
L7: IDR | M7: 0.11 | N7: 0.02 | Q7: con: inc.PPN11%
D8: Belum ada data revenue dan pajak
B9: REVENUE (IDR) | F9: =SUM(F8:F8) | L9: =SUM(L8:L8) | M9: =SUM(M8:M8) | N9: =SUM(N8:N8) | O9: =SUM(O8:O8)
B24: PAJAK PENGELUARAN
B25: Date | C25: # | D25: Detail/Description | F25: Transaction Value | G25: Currency | H25: Currency Exchange | I25: PPN | K25: PPh (pasal 21) | M25: PPh (pasal 23) | O25: PPh (pasal 26)
I26: Transaction | J26: PPN | K26: Transaction | L26: PPh - 21 | M26: Transaction | N26: PPh - 23 | O26: Transaction | P26: PPh - 26
D27: Belum ada data pajak | G27: IDR | H27: 1
B28: PENERIMAAN NEGARA (TAX) (IDR) | I28: PPN | J28: =SUM(J27:J27) | K28: PPh | L28: =SUM(L27:L27) | M28: PPh | N28: =SUM(N27:N27) | O28: PPh | P28: =SUM(P27:P27) | Q28: -
B37: PENERIMAAN NEGARA (TAX) (IDR) | I37: PPN | J37: =SUM(J27:J36) | K37: PPh | L37: =SUM(L27:L36) | M37: PPh | N37: =SUM(N27:N36) | O37: PPh | P37: =SUM(P27:P36)
B39: PENGELUARAN
B40: Date | C40: # | D40: Activity | E40: Source | F40: Jumlah | G40: Currency | H40: urrency Exchange | I40: Biaya Research (R&D) | J40: Biaya Sewa Peralatan | K40: Biaya Interpretasi Log Data | L40: Biaya Operasi | M40: diofavian | N40: Administrasi | O40: Pembelian Barang | P40: Sewa Kantor | Q40: Kesehatan | R40: Bisnis Dev | S40: asdasd | T40: makanan jepang | U40: aaaaa | V40: bbbbb | W40: asdsad | X40: dfgdfgdfgd | Y40: 12312
D41: keysha , nabil
B42: 47830 | C42: 1 | D42: 23434 | E42: BRI | F42: 220000 | G42: USD | H42: 10000 | M42: 220000
D43: -
B44: 47848 | C44: 2 | D44: asdasd | E44: Advance | F44: 234234 | G44: IDR | H44: 1 | S44: 234234
D45: Accommodation
B46: 47848 | C46: 3 | D46: qweqw | E46: BRI | F46: 138282273129 | G46: GBP | H46: 1123123 | L46: 138282273129
D47: Allowance
B48: 47848 | C48: 4 | D48: 87987000 | E48: BNI | F48: 98098000 | G48: IDR | H48: 1 | L48: 98098000
D49: keysha
B50: 47757 | C50: 5 | D50: sdasd | E50: Mandiri | F50: 14664 | G50: USD | H50: 1222 | M50: 14664
B51: 47848 | C51: 6 | D51: 3234234 | E51: Mandiri | F51: 234234 | G51: IDR | H51: 1 | M51: 234234
B52: 47848 | C52: 7 | D52: 23 | E52: Mandiri | F52: 13838729 | G52: EUR | H52: 1123 | M52: 13838729
D53: OPERATION COST AND OFFICE - Expenses Report
B54: Expense#1 | C54: : | D54: Gudang
D55: 123123
B56: 47848 | C56: 8 | D56: 123123 | E56: BCA | F56: 123123 | G56: IDR | H56: 1 | Y56: 123123
D57: Meal
B58: 47848 | C58: 9 | D58: werw | E58: BRI | F58: 123123 | G58: IDR | H58: 1 | L58: 123123
D59: nabil
B60: 47848 | C60: 10 | D60: reza | E60: BCA | F60: 30000 | G60: IDR | H60: 1 | M60: 30000
B61: Expense#2 | C61: : | D61: sasdas
D62: 123123
B63: 47848 | C63: 11 | D63: 123123 | E63: Advance | F63: 101 | G63: USD | H63: 101 | Y63: 101
D64: Allowance
B65: 47848 | C65: 12 | D65: 234234 | E65: Advance | F65: 234324324 | G65: IDR | H65: 1 | L65: 234324324
D66: Rental Tool
B67: 47848 | C67: 13 | D67: 234 | E67: Advance | F67: 57776 | G67: USD | H67: 14444 | J67: 57776
B68: Expense#3 | C68: : | D68: werwerewr
D69: Accommodation , Transportation
B70: 47848 | C70: 14 | D70: werwerwer | E70: Mandiri | F70: 281106 | G70: EUR | H70: 12222 | L70: 281106
D71: Meal , Shipping
B72: 47848 | C72: 15 | D72: we | E72: BRI | F72: 146664 | G72: EUR | H72: 12222 | L72: 146664
D73: Accommodation
B74: 47848 | C74: 16 | D74: 23423423 | E74: BCA | F74: 2888262 | G74: USD | H74: 12343 | L74: 2888262
D75: Shipping
B76: 47848 | C76: 17 | D76: 23434 | E76: BRI | F76: 28104 | G76: EUR | H76: 12 | L76: 28104
B77: Expense#4 | C77: : | D77: 1234567890
D78: Accommodation , Allowance
B79: 47848 | C79: 18 | D79: 123123 | E79: Advance | F79: 123123 | G79: IDR | H79: 1 | L79: 123123
D80: Accommodation
B81: 47848 | C81: 19 | D81: 324234 | E81: Advance | F81: 234324 | G81: IDR | H81: 1 | L81: 234324
D82: Transportation
B83: 47704 | C83: 20 | D83: 234324 | E83: BCA | F83: 134772 | G83: USD | H83: 11231 | L83: 134772
B84: Expense#5 | C84: : | D84: werwer
D85: Accommodation , Transportation
B86: 47848 | C86: 21 | D86: wqew | E86: Advance | F86: 123123 | G86: IDR | H86: 1 | L86: 123123
B87: Expense#6 | C87: : | D87: asdasd
D88: Rental Tool
B89: 47848 | C89: 22 | D89: wqeqwe | E89: Advance | F89: 123123 | G89: IDR | H89: 1 | J89: 123123
B90: 47848 | C90: 23 | D90: 213123 | E90: Advance | F90: 247126 | G90: USD | H90: 11233 | J90: 247126
B91: Expense#7 | C91: : | D91: lala
D92: Allowance , Transportation
B93: 47848 | C93: 24 | D93: jsj | E93: Advance | F93: 646 | G93: IDR | H93: 1 | L93: 646
B94: TOTAL | I94: 0 | J94: 428025 | K94: 0 | L94: 138618778700 | M94: 14337627 | N94: 0 | O94: 0 | P94: 0 | Q94: 0 | R94: 0 | S94: 234234 | T94: 0 | U94: 0 | V94: 0 | W94: 0 | X94: 0 | Y94: 123224
D95: Biaya Bank
B96: 45657 | C96: 1 | D96: Total Biaya Transaksi Bank selama 1 tahun | F96: 1998587 | G96: IDR | H96: 1 | M96: =$F96*$H96
D97: OPERATION COST AND OFFICE - Expenses Report
B98: Nama Lengkap
B99: Direktur
D100: Airplane
B101: 45329 | C101: 2 | D101: Airplane Ticket CGK-PLM | F101: 1608000 | G101: IDR | H101: 1 | I101: =$H101*$F101
B102: 45355 | C102: 3 | D102: Airplane Ticket PLM-CGK | F102: 1119500 | G102: IDR | H102: 1 | I102: =$H102*$F102
D103: Land Transportation
B104: 45329 | C104: 4 | D104: Taxi Bintaro-CGK | F104: 250000 | G104: IDR | H104: 1 | I104: =$H104*$F104
B105: 45330 | C105: 5 | D105: Rental Mobil Pajero 1 Hari | F105: 900000 | G105: IDR | H105: 1 | I105: =$H105*$F105
B106: 45330 | C106: 6 | D106: Rental Mobil Pajero Sebulan | F106: 18000000 | G106: IDR | H106: 1 | I106: =$H106*$F106
B107: 45355 | C107: 7 | D107: Taxi CGK-Bintaro | F107: 250000 | G107: IDR | H107: 1 | I107: =$H107*$F107
B108: 45355 | C108: 8 | D108: Fuel | F108: 1498484 | G108: IDR | H108: 1 | I108: =$H108*$F108
B109: 45355 | C109: 9 | D109: Toll Fee | F109: 378000 | G109: IDR | H109: 1 | I109: =$H109*$F109
D110: Hotel and Loundry
B111: 45329 | C111: 10 | D111: Hotel 7 Feb-8 Feb 2024 (1 days) | F111: 200000 | G111: IDR | H111: 1 | I111: =F111
B112: 45329 | C112: 11 | D112: Hotel Prabumulih 8 Feb- 7 Mar 2024 (1 Month) | F112: 3300000 | G112: IDR | H112: 1 | I112: =F112
B113: 45355 | C113: 12 | D113: Laundry 27 days 1 Persons @ 50K IDR/day | F113: 1350000 | G113: IDR | H113: 1 | I113: =F113
D114: Logistik
B115: 45329 | C115: 13 | D115: Gloves | F115: 58500 | G115: IDR | H115: 1 | N115: =F115
B116: 45341 | C116: 14 | D116: Battery A3 | F116: 82100 | G116: IDR | H116: 1 | N116: =F116
B117: 45341 | C117: 15 | D117: Steker | F117: 14000 | G117: IDR | H117: 1 | N117: =F117
B118: 45344 | C118: 16 | D118: Gloves | F118: 65000 | G118: IDR | H118: 1 | N118: =F118
B119: 45347 | C119: 17 | D119: White Marker | F119: 19000 | G119: IDR | H119: 1 | N119: =F119
B120: 45350 | C120: 18 | D120: Internet Data | F120: 87000 | G120: IDR | H120: 1 | N120: =F120
D121: Entertaiment on field Site
B122: 45355 | C122: 19 | D122: Meal Crew's Operational | F122: 1966300 | G122: IDR | H122: 1 | I122: =F122
D123: Meal Allowance
B124: 45355 | C124: 20 | D124: Meals 27 days 1 Persons @ 150K IDR/day | F124: 4050000 | G124: IDR | H124: 1 | I124: =F124
...

Sheet Laba rugi -2030
B3: PT. EXSPAN WIRELINE INDONESIA | G3: PT. EXSPAN WIRELINE INDONESIA
B4: LABA RUGI | TAHUN 2030 | G4: NERACA |TAHUN YANG BERAKHIR, 31 DESEMBER 2030
D6: PT. Exspan Wireline Indonesia | I6: PT. Exspan Wireline Indonesia
D7: (Rp) | I7: (Rp)
B8: PENDAPATAN | G8: AKTIVA
C9: PENDAPATAN LANGSUNG | D9: Rp | E9: 0 | G9: AKTIVA LANCAR
C10: PENDAPATAN LAIN LAIN | D10: Rp | E10: 0 | H10: KAS DAN SETARA KAS TAHUN SEBELUMNYA | I10: Rp | J10: 0
H11: KAS DAN SETARA KAS TAHUN LAPORAN | I11: Rp | J11: =E50-'Business Summary'!E13
B12: TOTAL PENDAPATAN | D12: Rp | E12: =SUM(E9:E11) | H12: PIUTANG USAHA | I12: Rp | J12: 0
H13: PAJAK BAYAR DI MUKA (pph23) | I13: Rp | J13: 0
B14: BEBAN LANGSUNG | H14: BIAYA BAYAR DI MUKA | I14: Rp | J14: 0
C15: BIAYA RESEARCH (R&D) | D15: Rp | E15: ='Revenue-Cost_2030'!I94 | H15: PIUTANG LAIN LAIN | I15: Rp | J15: 0
C16: BIAYA SEWA PERALATAN | D16: Rp | E16: ='Revenue-Cost_2030'!J94 | H16: TOTAL AKTIVA LANCAR | I16: Rp | J16: =SUM(J10:J15)
C17: BIAYA INTERPRETASI LOG DATA | D17: Rp | E17: ='Revenue-Cost_2030'!K94
C18: BIAYA OPERASI | D18: Rp | E18: ='Revenue-Cost_2030'!L94 | G18: ACTIVA TETAP
C19: DIOFAVIAN | D19: Rp | E19: ='Revenue-Cost_2030'!M94
B20: TOTAL BIAYA LANGSUNG | D20: Rp | E20: =SUM(E15:E19) | H20: INVENTARIS KANTOR | I20: Rp | J20: 0
B22: BEBAN TIDAK LANGSUNG | H22: TOTAL AKTIVA TETAP | I22: Rp | J22: =J20
D23: Rp | E23: 0
B24: TOTAL BIAYA TIDAK LANGSUNG | D24: Rp | E24: =SUM(E23:E23) | G24: ACTIVA LAIN LAIN | J24: 0
J25: 0
B26: BIAYA ADMINISTRASI DAN UMUM | H26: TOTAL AKTIVA LAIN LAIN | I26: Rp | J26: =SUM(J25:J25)
C27: ADMINISTRASI | D27: Rp | E27: ='Revenue-Cost_2030'!N94
C28: PEMBELIAN BARANG | D28: Rp | E28: ='Revenue-Cost_2030'!O94 | G28: TOTAL AKTIVA | I28: Rp | J28: =J26+J22+J16
C29: SEWA KANTOR | D29: Rp | E29: ='Revenue-Cost_2030'!P94
C30: KESEHATAN | D30: Rp | E30: ='Revenue-Cost_2030'!Q94 | G30: HUTANG DAN MODAL
C31: BISNIS DEV | D31: Rp | E31: ='Revenue-Cost_2030'!R94
C32: ASDASD | D32: Rp | E32: ='Revenue-Cost_2030'!S94 | G32: HUTANG LANCAR
C33: MAKANAN JEPANG | D33: Rp | E33: ='Revenue-Cost_2030'!T94 | H33: HUTANG USAHA | I33: Rp | J33: 0
C34: AAAAA | D34: Rp | E34: ='Revenue-Cost_2030'!U94 | H34: HUTANG GAJI | I34: Rp | J34: 0
C35: BBBBB | D35: Rp | E35: ='Revenue-Cost_2030'!V94 | H35: HUTANG PEMEGANG SAHAM | I35: Rp | J35: 0
C36: ASDSAD | D36: Rp | E36: ='Revenue-Cost_2030'!W94 | H36: BIAYA YANG MASIH HARUS DI BAYAR | I36: Rp | J36: 0
C37: DFGDFGDFGD | D37: Rp | E37: ='Revenue-Cost_2030'!X94
C38: 12312 | D38: Rp | E38: ='Revenue-Cost_2030'!Y94 | H38: TOTAL HUTANG LANCAR | J38: =SUM(J33:J36)
B39: TOTAL BIAYA ADMINISTRASI DAN UMUM | D39: Rp | E39: =SUM(E27:E38)
G40: MODAL
B41: TOTAL BIAYA | D41: Rp | E41: =E20+E24+E39 | H41: MODAL SAHAM | I41: Rp | J41: 0
H42: LABA DI TAHAN | I42: Rp | J42: 0
B43: PENDAPATAN/BEBAN LAIN LAIN | H43: TOTAL LABA (RUGI) DITAHAN | I43: Rp | J43: =J28-J38-J41-J42
C44: PENDAPATAN LAIN LAIN | D44: Rp | E44: 0 | H44: TOTAL MODAL | I44: Rp | J44: =SUM(J41:J43)
B46: LABA RUGI SEBELUM PAJAK | D46: Rp | E46: =E12-E41 | G46: TOTAL HUTANG DAN MODAL | I46: Rp | J46: =J44+J38
B48: CORPORATE TAX (PPh 29) | D48: Rp | E48: 0
B50: LABA / RUGI BERSIH | D50: Rp | E50: =E46-E48
B54: Nama Lengkap | G54: Nama Lengkap
B55: Direktur | G55: Direktur

Sheet Business Summary
B3: PT. EXSPAN WIRELINE INDONESIA
B4: BUSINESS SUMMARY | TAHUN 2030
B6: # | C6: Items | D6: Amount
B7: 1 | C7: Revenue | D7: Rp | E7: =SUM('Revenue-Cost_2030'!L8:L8)
B8: 2 | C8: Revenue Diterima (Setelah Pajak) | D8: Rp | E8: =E7-SUM('Revenue-Cost_2030'!N8:N8)
B9: 3 | C9: Biaya | D9: Rp | E9: =SUM('Revenue-Cost_2030'!I94:Y94)
B10: 4 | C10: Profit SebelumTax | D10: Rp | E10: =E7-E9
B11: 5 | C11: PPh Badan (22%*50%) | D11: Rp | E11: =E10*22%*50%
B12: 6 | C12: PPh 23 Dipotong oleh client | D12: Rp | E12: =SUM('Revenue-Cost_2030'!N8:N8)
B13: 7 | C13: Kekurangan Bayar PPh Badan | D13: Rp | E13: =E11-E12
B14: 8 | C14: Profit After Tax | D14: Rp | E14: =E10-E13
B15: 9 | C15: Deviden Dibagi | D15: Rp | E15: =E14-E16
B16: 10 | C16: Profit Ditahan | D16: Rp | E16: 0
B18: DEVIDEN
B19: # | C19: Nama Lengkap | D19: Rp | E19: Amount
