Workbook

Sheet Revenue-Cost_2027
B1: Daily Report - Balance Calculation Operation Cost
B2: Project | C2: : | D2: REVENUE vs OPERATION COST Tahun 2027
B3: Date | C3: : | D3: Januari - Desember 2027
B5: REVENUE & TAX
B6: Invoice Date | C6: # | D6: Detail/Description | F6: INVOICE VALUE | G6: Currency | H6: Currency Exchange | I6: INVOICE Number | J6: Client | K6: Receive Date | L6: AMOUNT RECEIVED | M6: PPn | N6: PPH (Pasal 23) | O6: Biaya transfer | P6: Remark
L7: IDR | M7: 0.11 | N7: 0.02 | Q7: con: inc.PPN11%
D8: Belum ada data revenue dan pajak
B9: REVENUE (IDR) | F9: =SUM(F8:F8) | L9: =SUM(L8:L8) | M9: =SUM(M8:M8) | N9: =SUM(N8:N8) | O9: =SUM(O8:O8)
B24: PAJAK PENGELUARAN
B25: Date | C25: # | D25: Detail/Description | F25: Transaction Value | G25: Currency | H25: Currency Exchange | I25: PPN | K25: PPh (pasal 21) | M25: PPh (pasal 23) | O25: PPh (pasal 26)
I26: Transaction | J26: PPN | K26: Transaction | L26: PPh - 21 | M26: Transaction | N26: PPh - 23 | O26: Transaction | P26: PPh - 26
C27: 1 | D27: Belum ada data pajak | G27: IDR | H27: 1
B28: PENERIMAAN NEGARA (TAX) (IDR) | I28: PPN | J28: =SUM(J27:J27) | K28: PPh | L28: =SUM(L27:L27) | M28: PPh | N28: =SUM(N27:N27) | O28: PPh | P28: =SUM(P27:P27) | Q28: -
B37: PENERIMAAN NEGARA (TAX) (IDR) | I37: PPN | J37: =SUM(J27:J36) | K37: PPh | L37: =SUM(L27:L36) | M37: PPh | N37: =SUM(N27:N36) | O37: PPh | P37: =SUM(P27:P36)
B39: PENGELUARAN
B40: Date | C40: # | D40: Activity | E40: Source | F40: Jumlah | G40: Currency | H40: urrency Exchange | I40: Biaya Operasi | J40: Biaya Research (R&D) | K40: Biaya Sewa Peralatan | L40: Biaya Interpretasi Log Data | M40: Administrasi | N40: Pembelian Barang | O40: Sewa Kantor | P40: Kesehatan | Q40: Bisnis Dev | R40: asdasd | S40: makanan jepang | T40: aaaaa | U40: bbbbb | V40: asdsad | W40: dfgdfgdfgd | X40: 12312
D41: Belum ada data single pengeluaran
D42: OPERATION COST AND OFFICE - Expenses Report
D43: Belum ada data batch pengeluaran
E44: TOTAL | F44: =SUM(F41:F43) | G44: IDR | H44: 1 | I44: 0 | J44: 0 | K44: 0 | L44: 0 | M44: 0 | N44: 0 | O44: 0 | P44: 0 | Q44: 0 | R44: 0 | S44: 0 | T44: 0 | U44: 0 | V44: 0 | W44: 0 | X44: 0
B45: 45323 | C45: 5 | D45: Gaji Januari 2024 _Yufitri | E45: BCA | F45: 2500000 | G45: IDR | H45: 1 | I45: =F45
B46: 45356 | C46: 6 | D46: Gaji Februari 2024 + raple gaji Januari 2024_Yufitri | E46: BCA | F46: 3500000 | G46: IDR | H46: 1 | I46: 3500000
B47: 45364 | C47: 7 | D47: Ralika Jaya Utama | Permbuatan alat Downhole Wireless Telemetry | E47: BCA | F47: 100000000 | G47: IDR | H47: 1 | J47: =$F47*$H47
B48: 45379 | C48: 8 | D48: Gaji Maret 2024_Yufitri | E48: BCA | F48: 3000000 | G48: IDR | H48: 1 | I48: 3000000
B49: 45388 | C49: 9 | D49: THR 2024_Yufitri | E49: BCA | F49: 3000000 | G49: IDR | H49: 1 | I49: 3000000
B50: 45413 | C50: 10 | D50: Data proccesing MTD 4 well, project Tomori-Alan | E50: BCA | F50: 122625000 | G50: IDR | H50: 1 | L50: 122625000
B51: 45416 | C51: 11 | D51: Gaji April_Yufitri | E51: BCA | F51: 3000000 | G51: IDR | H51: 1 | I51: 3000000
B52: 45418 | C52: 12 | D52: Ralika Jaya Utama | Permbuatan alat Downhole Wireless Telemetry | E52: BRI | F52: 100000000 | G52: IDR | H52: 1 | J52: =$F52*$H52
B53: 45422 | C53: 13 | D53: Aro Energy | Moving slickline dari Duri (Toni Supriadi) ke Sungai lilin | E53: BCA | F53: 18000000 | G53: IDR | H53: 1 | I53: =$F53*$H53
B54: 45446 | C54: 14 | D54: ALFA Service TLJ-58 Pertamina Zona#4 - Rental Tool | E54: BCA | F54: 29640916 | G54: IDR | H54: 1 | K54: =$F54*$H54
B55: 45446 | C55: 15 | D55: PT Laka Indonesia | Wastafel for WIKA Anantara Ubud Bali | E55: BCA | F55: 300000000 | G55: IDR | H55: 1 | I55: =$F55*$H55
B56: 45446 | C56: 16 | D56: Gaji Mei_Yufitri | E56: BCA | F56: 3000000 | G56: IDR | H56: 1 | I56: 3000000
B57: 45447 | C57: 17 | D57: ALFA Service JRK-193 Pertamina Zona#4 - Rental Tool | E57: BCA | F57: 29640916 | G57: IDR | H57: 1 | K57: =$F57*$H57
B58: 45473 | C58: 18 | D58: Gaji Juni 2024_Yufitri | E58: BCA | F58: 3000000 | G58: IDR | H58: 1 | I58: 3000000
B59: 45473 | C59: 19 | D59: Downhole Sampling tool #1-1 GARINDO SARANA BARU | E59: BCA | F59: 39800000 | G59: IDR | H59: 1 | N59: 3980000
B60: 45476 | C60: 20 | D60: Kekurangan (PPN ) ke PT Garindo sarana Baru (Downhole Sampling) | E60: BCA | F60: 3582000 | G60: IDR | H60: 1 | N60: 3582000
B61: 45478 | C61: 21 | D61: Repair ESOR panel & Fabricate dummy test load, Payment#2 | E61: BRI | F61: 25000000 | G61: IDR | H61: 1 | I61: =$F61
B62: 45480 | C62: 22 | D62: PT Laka Indonesia | Wastafel for WIKA Anantara Ubud Bali | E62: BCA | F62: 25000000 | G62: IDR | H62: 1 | I62: =$F62*$H62
B63: 45483 | C63: 23 | D63: Pembelian Lisence Sonoechometer to PT Weebz Mandiri | E63: BCA | F63: 16650000 | G63: IDR | H63: 1 | Q63: =$F63*$H63
B64: 45492 | C64: 24 | D64: PT Laka Indonesia | Wastafel for WIKA Anantara Ubud Bali | E64: BCA | F64: 25000000 | G64: IDR | H64: 1 | I64: =$F64*$H64
B65: 45493 | C65: 25 | D65: Repair ESOR panel & Fabricate dummy test load, Payment#1 | E65: BCA | F65: 20000000 | G65: IDR | H65: 1 | I65: =$F65
B66: 45501 | C66: 26 | D66: Gaji Juli 2024_Yufitri | E66: BCA | F66: 3000000 | G66: IDR | H66: 1 | I66: 3000000
B67: 45501 | C67: 27 | D67: Handphone Operational untuk Secretary (Yufitri) | E67: BCA | F67: 2600000 | G67: IDR | H67: 1 | N67: 2600000
B68: 45502 | C68: 28 | D68: Ralika Jaya Utama | Permbuatan alat injeksi listrik (EAS) | E68: BRI | F68: 100000000 | G68: IDR | H68: 1 | J68: =$F68*$H68
B69: 45519 | C69: 29 | D69: MUTRI | Sewa ruangan kantor BBC 2 bulan | E69: BCA | F69: 11270000 | G69: IDR | H69: 1 | Q69: =$F69*$H69
B70: 45519 | C70: 30 | D70: Downhole Sampling tool #1-2 GARINDO SARANA BARU | E70: BCA | F70: 53835000 | G70: IDR | H70: 1 | N70: =F70
B71: 45525 | C71: 31 | D71: Data proccesing TGB-33 DAN TIS (RBG-3b)-Alan | E71: BCA | F71: 101120000 | G71: IDR | H71: 1 | L71: =F71
B72: 45535 | C72: 32 | D72: Gaji Agustus 2024_Yufitri | E72: BCA | F72: 3000000 | G72: IDR | H72: 1 | I72: =F72
B73: 45537 | C73: 33 | D73: ALFA Service JRK-163 Pertamina Zona#4 - Rental Tool | E73: BCA | F73: 29640916 | G73: IDR | H73: 1 | K73: =$F73*$H73
B74: 45539 | C74: 34 | D74: MUTRI | Penambahan modal biaya kerja | E74: BRI | F74: 100000000 | G74: IDR | H74: 1 | Q74: =$F74*$H74
B75: 45548 | C75: 35 | D75: Ralika Jaya Utama | Permbuatan alat EMR | E75: BRI | F75: 150000000 | G75: IDR | H75: 1 | J75: =$F75*$H75
B76: 45556 | C76: 36 | D76: Downhole Sampling tool #2 GARINDO SARANA BARU | E76: BCA | F76: 34299000 | G76: IDR | H76: 1 | N76: =F76
B77: 45568 | C77: 37 | D77: Gaji fitri bulan september 2024 | E77: BRI | F77: 3000000 | G77: IDR | H77: 1 | I77: =F77
B78: 45568 | C78: 38 | D78: Gaji fitri bulan October 2024 | E78: BRI | F78: 3000000 | G78: IDR | H78: 1 | I78: =F78
B79: 45569 | C79: 41 | D79: PLT Service TGB-033 Pertamina Cirebon - Rental Tool | E79: BCA | F79: 16165271 | G79: IDR | H79: 1 | K79: =$F79*$H79
B80: 45569 | C80: 39 | D80: ALFA Service TGB-033 Pertamina Cirebon - Rental Tool | E80: BCA | F80: 25967616 | G80: IDR | H80: 1 | K80: =$F80*$H80
B81: 45569 | C81: 40 | D81: MFC Service TGB-033 Pertamina Cirebon - Rental Tool | E81: BCA | F81: 32101247 | G81: IDR | H81: 1 | K81: =$F81*$H81
B82: 45572 | C82: 42 | D82: ALFA Service JRK-095 Pertamina Zona#4 - Rental Tool | E82: BCA | F82: 29640916 | G82: IDR | H82: 1 | K82: =$F82*$H82
B83: 45576 | C83: 43 | D83: MPLT/GR-CCL/ALFA TIS - Rental Tool | E83: BCA | F83: 74291457 | G83: IDR | H83: 1 | K83: =$F83*$H83
B84: 45581 | C84: 44 | D84: PT Laka Indonesia | Project Lampu Taman Istana Negara Jakarta | E84: BRI | F84: 100000000 | G84: IDR | H84: 1 | I84: =$F84*$H84
B85: 45589 | C85: 45 | D85: Data Processing 8 Well Alan Project SIJAK | E85: BRI | F85: 144000000 | G85: IDR | H85: 1 | L85: =F85
B86: 45601 | C86: 46 | D86: Sales fee 2 Well Integrity Pertamina Z.4 | E86: BRI | F86: 38838700 | G86: IDR | H86: 1 | I86: =$F86*$H86
B87: 45625 | C87: 47 | D87: MUTRI | Penambahan modal biaya kerja 3rd | E87: BRI | F87: 75000000 | G87: IDR | H87: 1 | Q87: =$F87*$H87
B88: 45625 | C88: 48 | D88: Gaji fitri bulan November 2024 | E88: BRI | F88: 3000000 | G88: IDR | H88: 1 | I88: =F88
B89: 45630 | C89: 49 | D89: Payment ke UPS Biaya Import pembelian sparepart dari Pei-Genesis | E89: BRI | F89: 777246 | G89: IDR | H89: 1 | N89: =F89
B90: 45631 | C90: 50 | D90: Ralika Jaya Utama | Permbuatan alat injeksi listrik (EAS) | E90: BRI | F90: 400000000 | G90: IDR | H90: 1 | J90: =$F90*$H90
B91: 45632 | C91: 51 | D91: Sewa Virtual Office 1th, 1jan25 - 31des25_BBC_ Ganesha Dwipaya B | E91: BCA | F91: 4995000 | G91: IDR | H91: 1 | O91: =F91
B92: 45644 | C92: 52 | D92: Team building EWI dengan team Well Intervention PEP Reg. 2 | E92: BCA | F92: 39201350 | G92: IDR | H92: 1 | I92: =$F92*$H92
B93: 45651 | C93: 53 | D93: Gaji Desember 2024 + Bomnus akhir tahun - 4 bulan_Yufitri | E93: BCA | F93: 15000000 | G93: IDR | H93: 1 | I93: =F93
B94: 45653 | C94: 54 | D94: KUPA | Pembelian Mesin Retort Horizontal 500 Lt Automatic Control | E94: BCA | F94: 141500000 | G94: IDR | H94: 1 | J94: =$F94*$H94
D95: Biaya Bank
B96: 45657 | C96: 1 | D96: Total Biaya Transaksi Bank selama 1 tahun | F96: 1998587 | G96: IDR | H96: 1 | M96: =$F96*$H96
D97: OPERATION COST AND OFFICE - Expenses Report
B98: Expense#1 | C98: : | D98: ALFA_ TLJ-58 (PEPZ4-Prabumulih field) SIJak- IC
D99: Transportation
D100: Transportation
B101: 45329 | C101: 2 | D101: Airplane Ticket CGK-PLM | F101: 1608000 | G101: IDR | H101: 1 | I101: =$H101*$F101
B102: 45355 | C102: 3 | D102: Airplane Ticket PLM-CGK | F102: 1119500 | G102: IDR | H102: 1 | I102: =$H102*$F102
D103: Transportation
B104: 45329 | C104: 4 | D104: Taxi Bintaro-CGK | F104: 250000 | G104: IDR | H104: 1 | I104: =$H104*$F104
B105: 45330 | C105: 5 | D105: Rental Mobil Pajero 1 Hari | F105: 900000 | G105: IDR | H105: 1 | I105: =$H105*$F105
B106: 45330 | C106: 6 | D106: Rental Mobil Pajero Sebulan | F106: 18000000 | G106: IDR | H106: 1 | I106: =$H106*$F106
B107: 45355 | C107: 7 | D107: Taxi CGK-Bintaro | F107: 250000 | G107: IDR | H107: 1 | I107: =$H107*$F107
B108: 45355 | C108: 8 | D108: Fuel | F108: 1498484 | G108: IDR | H108: 1 | I108: =$H108*$F108
B109: 45355 | C109: 9 | D109: Toll Fee | F109: 378000 | G109: IDR | H109: 1 | I109: =$H109*$F109
D110: Accommodation
B111: 45329 | C111: 10 | D111: Hotel 7 Feb-8 Feb 2024 (1 days) | F111: 200000 | G111: IDR | H111: 1 | I111: =F111
B112: 45329 | C112: 11 | D112: Hotel Prabumulih 8 Feb- 7 Mar 2024 (1 Month) | F112: 3300000 | G112: IDR | H112: 1 | I112: =F112
B113: 45355 | C113: 12 | D113: Laundry 27 days 1 Persons @ 50K IDR/day | F113: 1350000 | G113: IDR | H113: 1 | I113: =F113
D114: Logistic
B115: 45329 | C115: 13 | D115: Gloves | F115: 58500 | G115: IDR | H115: 1 | N115: =F115
B116: 45341 | C116: 14 | D116: Battery A3 | F116: 82100 | G116: IDR | H116: 1 | N116: =F116
B117: 45341 | C117: 15 | D117: Steker | F117: 14000 | G117: IDR | H117: 1 | N117: =F117
B118: 45344 | C118: 16 | D118: Gloves | F118: 65000 | G118: IDR | H118: 1 | N118: =F118
B119: 45347 | C119: 17 | D119: White Marker | F119: 19000 | G119: IDR | H119: 1 | N119: =F119
B120: 45350 | C120: 18 | D120: Internet Data | F120: 87000 | G120: IDR | H120: 1 | N120: =F120
D121: Meal
B122: 45355 | C122: 19 | D122: Meal Crew's Operational | F122: 1966300 | G122: IDR | H122: 1 | I122: =F122
D123: Meal
B124: 45355 | C124: 20 | D124: Meals 27 days 1 Persons @ 150K IDR/day | F124: 4050000 | G124: IDR | H124: 1 | I124: =F124
...

Sheet Laba rugi -2027
B3: PT. EXSPAN WIRELINE INDONESIA | G3: PT. EXSPAN WIRELINE INDONESIA
B4: LABA RUGI | TAHUN 2024 | G4: NERACA |TAHUN YANG BERAKHIR, 31 DESEMBER 2024 | K4: CATATAN KEAMANAN
K5: Kolom ini aman dari overwrite sistem.
D6: PT. Exspan Wireline Indonesia | I6: PT. Exspan Wireline Indonesia | K6: Diverifikasi pada: 2026-04-01 02:51
D7: (Rp) | I7: (Rp)
B8: PENDAPATAN | G8: AKTIVA
C9: PENDAPATAN LANGSUNG | D9: Rp | E9: =SUM('Revenue-Cost_2027'!L8:'Revenue-Cost_2027'!L22) | G9: AKTIVA LANCAR
C10: PENDAPATAN LAIN LAIN | D10: Rp | E10: =SUM('Revenue-Cost_2027'!L8:'Revenue-Cost_2027'!L22) | H10: KAS DAN SETARA KAS TAHUN SEBELUMNYA | I10: Rp | J10: 0
H11: KAS DAN SETARA KAS TAHUN LAPORAN | I11: Rp | J11: =E46-'Business Summary'!E13
B12: TOTALPENDAPATAN | D12: Rp | E12: =SUM(E9:E11) | H12: PIUTANG USAHA | I12: Rp | J12: 0
H13: PAJAK BAYAR DI MUKA (pph23) | I13: Rp | J13: 0
B14: BEBAN LANGSUNG | H14: BIAYA BAYAR DI MUKA | I14: Rp | J14: 0
C15: Biaya Operasi | D15: Rp | E15: ='Revenue-Cost_2027'!I44 | H15: PIUTANG LAIN LAIN | I15: Rp | J15: 0
C16: Biaya research (R & D) | D16: Rp | E16: ='Revenue-Cost_2027'!J44 | H16: TOTAL AKTIVA LANCAR | I16: Rp | J16: =SUM(J10:J15)
C17: BIAYA SEWA PERALATAN | D17: Rp | E17: ='Revenue-Cost_2027'!K44
C18: BIAYA Data Processing | D18: Rp | E18: ='Revenue-Cost_2027'!L44 | G18: ACTIVA TETAP
H20: INVENTARIS KANTOR | I20: Rp | J20: 0
B21: TOTAL BIAYA LANGSUNG | D21: Rp | E21: =SUM(E15:E20)
H22: TOTAL AKTIVA TETAP | I22: Rp | J22: =J20
B23: BEBAN TIDAK LANGSUNG | E23: ='Revenue-Cost_2027'!Q44
G24: ACTIVA LAIN LAIN | J24: 0
D25: Rp | J25: 0
H26: TOTAL AKTIVA LAIN LAIN | I26: Rp | J26: =SUM(J25:J25)
B27: TOTAL BIAYA TIDAK LANGSUNG | D27: Rp | E27: =SUM(E22:E26)
G28: TOTAL AKTIVA | I28: Rp | J28: =J26+J22+J16
B29: BIAYA ADMINISTRASI DAN UMUM
C30: BIAYA ADMINISTRASI | D30: Rp | E30: ='Revenue-Cost_2027'!M44 | G30: HUTANG DAN MODAL
C31: BIAYA PEMBELIAN Barang | D31: Rp | E31: ='Revenue-Cost_2027'!N44
C32: BIAYA SEWA KANTOR | D32: Rp | E32: ='Revenue-Cost_2027'!O44 | G32: HUTANG LANCAR
C33: BIAYA KESEHATAN | D33: Rp | E33: ='Revenue-Cost_2027'!P44 | H33: HUTANG USAHA | I33: Rp | J33: 0
H34: HUTANG GAJI | I34: Rp | J34: 0
B35: TOTAL BIAYA ADMINISTRASI DAN UMUM | D35: Rp | E35: =SUM(E30:E34) | H35: HUTANG PEMEGANG SAHAM | I35: Rp | J35: 0
H36: BIAYA YANG MASIH HARUS DI BAYAR | I36: Rp | J36: 0
B37: TOTAL BIAYA | D37: Rp | E37: =E35+E21+E27
H38: TOTAL HUTANG LANCAR | J38: =SUM(J33:J36)
B39: PENDAPATAN/BEBAN LAIN LAIN | D39: Rp
C40: PENDAPATAN LAINNYA | D40: Rp | E40: 0 | G40: MODAL
H41: MODAL SAHAM | I41: Rp | J41: 0
B42: LABA RUGI SEBELUM PAJAK | D42: Rp | E42: =E12-E37 | H42: LABA DI TAHAN | I42: Rp | J42: 0
H43: TOTAL LABA (RUGI) DITAHAN | I43: Rp | J43: =J28-J38-J41-J42
B44: CORPORATE TAX (PPh 29) | D44: Rp | E44: 0 | H44: TOTAL MODAL | I44: Rp | J44: =SUM(J41:J43)
B46: LABA / RUGI BERSIH | E46: =E42-E44 | G46: TOTAL HUTANG DAN MODAL | I46: Rp | J46: =J44+J38
B50: Direktur | G50: Direktur

Sheet Business Summary
B3: PT. EXSPAN WIRELINE INDONESIA
B4: BUSINESS SUMMARY | TAHUN 2027
B6: # | C6: Items | D6: Amount
B7: 1 | C7: Revenue | D7: Rp | E7: =SUM('Revenue-Cost_2027'!L8:'Revenue-Cost_2027'!L22)
B8: 2 | C8: Revenue Diterima (Setelah Pajak) | D8: Rp | E8: =E7-SUM('Revenue-Cost_2027'!N8:'Revenue-Cost_2027'!N22)
B9: 3 | C9: Biaya | D9: Rp | E9: =SUM('Revenue-Cost_2027'!I44:Q44)
B10: 4 | C10: Profit SebelumTax | D10: Rp | E10: =E7-E9
B11: 5 | C11: PPh Badan (22%*50%) | D11: Rp | E11: =E10*22%*50%
B12: 6 | C12: PPh 23 Dipotong oleh client | D12: Rp | E12: =SUM('Revenue-Cost_2027'!N8:'Revenue-Cost_2027'!N22)
B13: 7 | C13: Kekurangan Bayar PPh Badan | D13: Rp | E13: =E11-E12
B14: 8 | C14: Profit After Tax | D14: Rp | E14: =E10-E13
B15: 9 | C15: Deviden Dibagi | D15: Rp | E15: =E14-E16
B16: 10 | C16: Profit Ditahan | D16: Rp | E16: 0
B18: DEVIDEN
B19: # | C19: Nama Lengkap | E19: Amount | G19: Pajak
