Workbook

Sheet Sheet1
B1: Daily Report - Balance Calculation Operation Cost
B2: Project | C2: : | D2: REVENUE vs OPERATION COST Tahun 2024
B3: Date | C3: : | D3: Januari - Desember 2024
B5: REVENUE & TAX
B6: Invoice Date | C6: # | D6: Detail/Description | F6: INVOICE VALUE | G6: Currency | H6: Currency Exchange | I6: INVOICE Number | J6: Client | K6: Receive Date | L6: AMOUNT RECEIVED | M6: PPn | N6: PPH (Pasal 23) | O6: Biaya transfer | P6: Remark
L7: IDR | M7: 0.11 | N7: 0.02
B8: 45302 | C8: 2 | D8: ALFA Service PDP-075 Pertamina Zona#4 | F8: 354210000 | G8: IDR | H8: 1 | I8: INV017 | J8: SI Jak | K8: 45350 | L8: 347125800 | M8: =(F8*11%) | N8: =(F8*2%) | O8: =F8-N8-L8 | P8: Pemungut
B9: 45301 | C9: 3 | D9: Revenue data procesing MTD_Tomori | F9: 150000000 | G9: IDR | H9: 1 | I9: INV015 | J9: TGE | K9: 45399 | L9: 166500000 | M9: =(F9*11%) | N9: =(F9*2%) | O9: 0 | Q9: inc.PPN11%
B10: 45302 | C10: 4 | D10: ALFA Service PDS-01ST Pertamina Zona#4 | F10: 354210000 | G10: IDR | H10: 1 | I10: INV019 | J10: SI Jak | K10: 45425 | L10: 347125800 | M10: =(F10*11%) | N10: =(F10*2%) | O10: =F10-N10-L10 | P10: Pemungut
B11: 45302 | C11: 5 | D11: ALFA Service JRK-254 Pertamina Zona#4 | F11: 354210000 | G11: IDR | H11: 1 | I11: INV018 | J11: SI Jak | K11: 45453 | L11: 347125800 | M11: =(F11*11%) | N11: =(F11*2%) | O11: =F11-N11-L11 | P11: Pemungut
B12: 45446 | C12: 6 | D12: ALFA Service TLJ-58 Pertamina Zona#4 | F12: 354210000 | G12: IDR | H12: 1 | I12: INV020 | J12: SI Jak | K12: 45497 | L12: 347125800 | M12: =(F12*11%) | N12: =(F12*2%) | O12: =F12-N12-L12 | P12: Pemungut
B13: 45447 | C13: 7 | D13: ALFA Service JRK-193 Pertamina Zona#4 | F13: 354210000 | G13: IDR | H13: 1 | I13: INV021 | J13: SI Jak | K13: 45516 | L13: 347125800 | M13: =(F13*11%) | N13: =(F13*2%) | O13: =F13-N13-L13 | P13: Pemungut
B14: 45539 | C14: 8 | D14: Revenue Repair Electric Assisted Stimulation Machine (no 23) | F14: 89000000 | G14: IDR | H14: 1 | I14: INV023 | J14: LBU | K14: 45553 | L14: =(89000000*98%)+9700000 | M14: =(F14*11%) | N14: =(F14*2%) | Q14: inc.PPN11%
B15: 45537 | C15: 9 | D15: ALFA Service JRK-163 Pertamina Zona#4 | F15: 354210000 | G15: IDR | H15: 1 | I15: INV022 | J15: SI Jak | K15: 45575 | L15: 347125800 | M15: =(F15*11%) | N15: =(F15*2%) | O15: =F15-N15-L15 | P15: Pemungut
B16: 45576 | C16: 10 | D16: Revenue Project TIS (no 28 ) | F16: 819200000 | G16: IDR | H16: 1 | I16: INV028 | J16: Barikin Sakti | K16: 45579 | L16: 892928000 | M16: =(F16*11%) | N16: =(F16*2%) | O16: =L16-(F16+M16-N16) | Q16: inc.PPN11%
B17: 45572 | C17: 11 | D17: ALFA Service JRK-095 Pertamina Zona#4 | F17: 354210000 | G17: IDR | H17: 1 | I17: INV027 | J17: SI Jak | K17: 45607 | L17: 347125800 | M17: =(F17*11%) | N17: =(F17*2%) | O17: =F17-N17-L17 | P17: Pemungut
B18: 45569 | C18: 12 | D18: ALFA Service TGB-033 Pertamina Cirebon | F18: 290000000 | G18: IDR | H18: 1 | I18: INV024 | J18: Elnusa | K18: 45646 | L18: 284197100 | M18: =(F18*11%) | N18: =(F18*2%) | O18: =F18-N18-L18 | P18: Pemungut
B19: 45569 | C19: 13 | D19: MFC Service TGB-033 Pertamina Cirebon | F19: 280000000 | G19: IDR | H19: 1 | I19: INV025 | J19: Elnusa | K19: 45653 | L19: 412577100 | M19: =(F19*11%) | N19: =(F19*2%) | O19: =F19+F20-L19-(N19+N20) | P19: Pemungut
B20: 45569 | C20: 14 | D20: PLT Service TGB-033 Pertamina Cirebon | F20: 141000000 | G20: IDR | H20: 1 | I20: INV026 | J20: Elnusa | M20: =(F20*11%) | N20: =(F20*2%) | P20: Pemungut
B21: 45657 | C21: 15 | D21: Bunga Bank 2024 | F21: 6925425 | G21: IDR | L21: =F21
B22: REVENUE (IDR) | F22: =SUM(F8:F21) | L22: =SUM(L8:L21) | M22: =SUM(M8:M21) | N22: =SUM(N8:N21)
B24: PAJAK PENGELUARAN
B25: Date | C25: # | D25: Detail/Description | F25: Transaction Value | G25: Currency | H25: Currency Exchange | I25: PPN | K25: PPh (pasal 21) | M25: PPh (pasal 23) | O25: PPh (pasal 26)
I26: Transaction | J26: PPN | K26: Transaction | L26: PPh - 21 | M26: Transaction | N26: PPh - 23 | O26: Transaction | P26: PPh - 26
B27: 45289 | D27: Tax PPN 11% (Project TGE MEPI Rimau Pembayaran Ke-2) | F27: 33836000 | J27: 33836000
B28: 45302 | D28: Tax PPN 11% (Project TGE MEPI Rimau Pembayaran Ke-2) | F28: 33836000 | J28: 33836000
B29: 45351 | D29: Tax PPN 11% (Project TGE MEPI Tomori) | F29: 16500000 | J29: 16500000
B30: 45567 | D30: Tax PPN 11% (Perbaikan Repair Electric Assisted Stimulation Machine) | F30: 9790000 | J30: 9790000
B31: 45546 | D31: Pinalty Telat bayar pajak PP21 Sewa tool ALFA 2023 | F31: 25439666 | L31: 25439666
B32: 45546 | D32: Tax PPN 11% pajak Inv-007 tahun 2023 sarulla project - Sibat | F32: 96126126 | J32: 97126126
B33: 45589 | D33: Penalty telat bayar pajak PPN project sarulla_INV-007_under Sibat | F33: 17716045
B34: 45593 | D34: Pemindahbukan dari double bayar (29 des 2023) utk PPN Inv-028 | F34: 33836000 | J34: 33836000
B35: 45607 | D35: Kekurangan pajak PPn Inv-028 (barikikn Sakti)(1/3 nya dari PBK pajak) | F35: 56276000 | J35: 56276000
B36: 45607 | D36: Kekurangan pajak final PPH 23 keuntungan perusahaan tahun 2023 | F36: 1726469 | N36: 1726469
B37: PENERIMAAN NEGARA (TAX) (IDR) | I37: PPN | J37: =SUM(J27:J36) | K37: PPh | L37: =SUM(L27:L36) | M37: PPh | N37: =SUM(N27:N36) | O37: PPh | P37: =SUM(P27:P36)
B39: PENGELUARAN
B40: Date | C40: # | D40: Activity | E40: Source | F40: Jumlah | G40: Currency | H40: urrency Exchange | I40: Biaya Operasi (Gaji, Tunjangan Lapangan, Training, THR, Transport, Meal, Hotel, loundry) | J40: Biaya research (R & D) | K40: BIAYA SEWA PERALATAN | L40: BIAYA INTEPRETASI LOG DATA | M40: ADMINISTRASI | N40: PEMBELIAN Barang | O40: SEWA KANTOR | P40: KESEHATAN | Q40: BISNIS DEV
B41: 45302 | C41: 1 | D41: ALFA Service PDP-075 Pertamina Zona#4 - Rental Tool | E41: BCA | F41: 29640916 | G41: IDR | H41: 1 | K41: =$F41*$H41
B42: 45302 | C42: 2 | D42: ALFA Service PDS-01ST Pertamina Zona#4 - Rental Tool | E42: BCA | F42: 29640916 | G42: IDR | H42: 1 | K42: =$F42*$H42
B43: 45302 | C43: 3 | D43: ALFA Service JRK-254 Pertamina Zona#4 - Rental Tool | E43: BCA | F43: 29640916 | G43: IDR | H43: 1 | K43: =$F43*$H43
B44: 45304 | C44: 4 | D44: Sales cost 4 Well Integrity Pertamina Z.4 | E44: BRI | F44: 77672400 | G44: IDR | H44: 1 | I44: =$F44*$H44
B45: 45323 | C45: 5 | D45: Gaji Januari 2024 _Yufitri | E45: BCA | F45: 2500000 | G45: IDR | H45: 1 | I45: =F45
B46: 45356 | C46: 6 | D46: Gaji Februari 2024 + raple gaji Januari 2024_Yufitri | E46: BCA | F46: 3500000 | G46: IDR | H46: 1 | I46: 3500000
B47: 45364 | C47: 7 | D47: Ralika Jaya Utama | Permbuatan alat Downhole Wireless Telemetry | E47: BCA | F47: 100000000 | G47: IDR | H47: 1 | J47: =$F47*$H47
B48: 45379 | C48: 8 | D48: Gaji Maret 2024_Yufitri | E48: BCA | F48: 3000000 | G48: IDR | H48: 1 | I48: 3000000
B49: 45388 | C49: 9 | D49: THR 2024_Yufitri | E49: BCA | F49: 3000000 | G49: IDR | H49: 1 | I49: 3000000
B50: 45413 | C50: 10 | D50: Data proccesing MTD 4 well, project Tomori-Alan | E50: BCA | F50: 122625000 | G50: IDR | H50: 1 | L50: 122625000
B51: 45416 | C51: 11 | D51: Gaji April_Yufitri | E51: BCA | F51: 3000000 | G51: IDR | H51: 1 | I51: 3000000
B52: 45418 | C52: 12 | D52: Ralika Jaya Utama | Permbuatan alat Downhole Wireless Telemetry | E52: BRI | F52: 100000000 | G52: IDR | H52: 1 | J52: =$F52*$H52
B53: 45422 | C53: 13 | D53: Aro Energy | Moving slickline dari Duri (Toni Supriadi) ke Sungai lilin | E53: BCA | F53: 18000000 | G53: IDR | H53: 1 | I53: =$F53*$H53
B54: 45446 | C54: 14 | D54: ALFA Service TLJ-58 Pertamina Zona#4 - Rental Tool | E54: BCA | F54: 29640916 | G54: IDR | H54: 1 | K54: =$F54*$H54
B55: 45446 | C55: 15 | D55: PT Laka Indonesia | Wastafel for WIKA Anantara Ubud Bali | E55: BCA | F55: 300000000 | G55: IDR | H55: 1 | I55: =$F55*$H55
B56: 45446 | C56: 16 | D56: Gaji Mei_Yufitri | E56: BCA | F56: 3000000 | G56: IDR | H56: 1 | I56: 3000000
B57: 45447 | C57: 17 | D57: ALFA Service JRK-193 Pertamina Zona#4 - Rental Tool | E57: BCA | F57: 29640916 | G57: IDR | H57: 1 | K57: =$F57*$H57
B58: 45473 | C58: 18 | D58: Gaji Juni 2024_Yufitri | E58: BCA | F58: 3000000 | G58: IDR | H58: 1 | I58: 3000000
B59: 45473 | C59: 19 | D59: Downhole Sampling tool #1-1 GARINDO SARANA BARU | E59: BCA | F59: 39800000 | G59: IDR | H59: 1 | N59: 3980000
B60: 45476 | C60: 20 | D60: Kekurangan (PPN ) ke PT Garindo sarana Baru (Downhole Sampling) | E60: BCA | F60: 3582000 | G60: IDR | H60: 1 | N60: 3582000
B61: 45478 | C61: 21 | D61: Repair ESOR panel & Fabricate dummy test load, Payment#2 | E61: BRI | F61: 25000000 | G61: IDR | H61: 1 | I61: =$F61
B62: 45480 | C62: 22 | D62: PT Laka Indonesia | Wastafel for WIKA Anantara Ubud Bali | E62: BCA | F62: 25000000 | G62: IDR | H62: 1 | I62: =$F62*$H62
B63: 45483 | C63: 23 | D63: Pembelian Lisence Sonoechometer to PT Weebz Mandiri | E63: BCA | F63: 16650000 | G63: IDR | H63: 1 | Q63: =$F63*$H63
B64: 45492 | C64: 24 | D64: PT Laka Indonesia | Wastafel for WIKA Anantara Ubud Bali | E64: BCA | F64: 25000000 | G64: IDR | H64: 1 | I64: =$F64*$H64
B65: 45493 | C65: 25 | D65: Repair ESOR panel & Fabricate dummy test load, Payment#1 | E65: BCA | F65: 20000000 | G65: IDR | H65: 1 | I65: =$F65
B66: 45501 | C66: 26 | D66: Gaji Juli 2024_Yufitri | E66: BCA | F66: 3000000 | G66: IDR | H66: 1 | I66: 3000000
B67: 45501 | C67: 27 | D67: Handphone Operational untuk Secretary (Yufitri) | E67: BCA | F67: 2600000 | G67: IDR | H67: 1 | N67: 2600000
B68: 45502 | C68: 28 | D68: Ralika Jaya Utama | Permbuatan alat injeksi listrik (EAS) | E68: BRI | F68: 100000000 | G68: IDR | H68: 1 | J68: =$F68*$H68
B69: 45519 | C69: 29 | D69: MUTRI | Sewa ruangan kantor BBC 2 bulan | E69: BCA | F69: 11270000 | G69: IDR | H69: 1 | Q69: =$F69*$H69
B70: 45519 | C70: 30 | D70: Downhole Sampling tool #1-2 GARINDO SARANA BARU | E70: BCA | F70: 53835000 | G70: IDR | H70: 1 | N70: =F70
B71: 45525 | C71: 31 | D71: Data proccesing TGB-33 DAN TIS (RBG-3b)-Alan | E71: BCA | F71: 101120000 | G71: IDR | H71: 1 | L71: =F71
B72: 45535 | C72: 32 | D72: Gaji Agustus 2024_Yufitri | E72: BCA | F72: 3000000 | G72: IDR | H72: 1 | I72: =F72
B73: 45537 | C73: 33 | D73: ALFA Service JRK-163 Pertamina Zona#4 - Rental Tool | E73: BCA | F73: 29640916 | G73: IDR | H73: 1 | K73: =$F73*$H73
B74: 45539 | C74: 34 | D74: MUTRI | Penambahan modal biaya kerja | E74: BRI | F74: 100000000 | G74: IDR | H74: 1 | Q74: =$F74*$H74
B75: 45548 | C75: 35 | D75: Ralika Jaya Utama | Permbuatan alat EMR | E75: BRI | F75: 150000000 | G75: IDR | H75: 1 | J75: =$F75*$H75
B76: 45556 | C76: 36 | D76: Downhole Sampling tool #2 GARINDO SARANA BARU | E76: BCA | F76: 34299000 | G76: IDR | H76: 1 | N76: =F76
B77: 45568 | C77: 37 | D77: Gaji fitri bulan september 2024 | E77: BRI | F77: 3000000 | G77: IDR | H77: 1 | I77: =F77
B78: 45568 | C78: 38 | D78: Gaji fitri bulan October 2024 | E78: BRI | F78: 3000000 | G78: IDR | H78: 1 | I78: =F78
B79: 45569 | C79: 41 | D79: PLT Service TGB-033 Pertamina Cirebon - Rental Tool | E79: BCA | F79: 16165271 | G79: IDR | H79: 1 | K79: =$F79*$H79
B80: 45569 | C80: 39 | D80: ALFA Service TGB-033 Pertamina Cirebon - Rental Tool | E80: BCA | F80: 25967616 | G80: IDR | H80: 1 | K80: =$F80*$H80
B81: 45569 | C81: 40 | D81: MFC Service TGB-033 Pertamina Cirebon - Rental Tool | E81: BCA | F81: 32101247 | G81: IDR | H81: 1 | K81: =$F81*$H81
B82: 45572 | C82: 42 | D82: ALFA Service JRK-095 Pertamina Zona#4 - Rental Tool | E82: BCA | F82: 29640916 | G82: IDR | H82: 1 | K82: =$F82*$H82
B83: 45576 | C83: 43 | D83: MPLT/GR-CCL/ALFA TIS - Rental Tool | E83: BCA | F83: 74291457 | G83: IDR | H83: 1 | K83: =$F83*$H83
B84: 45581 | C84: 44 | D84: PT Laka Indonesia | Project Lampu Taman Istana Negara Jakarta | E84: BRI | F84: 100000000 | G84: IDR | H84: 1 | I84: =$F84*$H84
B85: 45589 | C85: 45 | D85: Data Processing 8 Well Alan Project SIJAK | E85: BRI | F85: 144000000 | G85: IDR | H85: 1 | L85: =F85
B86: 45601 | C86: 46 | D86: Sales fee 2 Well Integrity Pertamina Z.4 | E86: BRI | F86: 38838700 | G86: IDR | H86: 1 | I86: =$F86*$H86
B87: 45625 | C87: 47 | D87: MUTRI | Penambahan modal biaya kerja 3rd | E87: BRI | F87: 75000000 | G87: IDR | H87: 1 | Q87: =$F87*$H87
B88: 45625 | C88: 48 | D88: Gaji fitri bulan November 2024 | E88: BRI | F88: 3000000 | G88: IDR | H88: 1 | I88: =F88
B89: 45630 | C89: 49 | D89: Payment ke UPS Biaya Import pembelian sparepart dari Pei-Genesis | E89: BRI | F89: 777246 | G89: IDR | H89: 1 | N89: =F89
B90: 45631 | C90: 50 | D90: Ralika Jaya Utama | Permbuatan alat injeksi listrik (EAS) | E90: BRI | F90: 400000000 | G90: IDR | H90: 1 | J90: =$F90*$H90
B91: 45632 | C91: 51 | D91: Sewa Virtual Office 1th, 1jan25 - 31des25_BBC_ Ganesha Dwipaya B | E91: BCA | F91: 4995000 | G91: IDR | H91: 1 | O91: =F91
B92: 45644 | C92: 52 | D92: Team building EWI dengan team Well Intervention PEP Reg. 2 | E92: BCA | F92: 39201350 | G92: IDR | H92: 1 | I92: =$F92*$H92
B93: 45651 | C93: 53 | D93: Gaji Desember 2024 + Bomnus akhir tahun - 4 bulan_Yufitri | E93: BCA | F93: 15000000 | G93: IDR | H93: 1 | I93: =F93
B94: 45653 | C94: 54 | D94: KUPA | Pembelian Mesin Retort Horizontal 500 Lt Automatic Control | E94: BCA | F94: 141500000 | G94: IDR | H94: 1 | J94: =$F94*$H94
D95: Biaya Bank
B96: 45657 | C96: 1 | D96: Total Biaya Transaksi Bank selama 1 tahun | F96: 1998587 | G96: IDR | H96: 1 | M96: =$F96*$H96
D97: OPERATION COST AND OFFICE - Expenses Report
B98: Expense#1 | C98: : | D98: ALFA_ TLJ-58 (PEPZ4-Prabumulih field) SIJak- IC
D99: Transportation
D100: Transportation
B101: 45329 | C101: 2 | D101: Airplane Ticket CGK-PLM | F101: 1608000 | G101: IDR | H101: 1 | I101: =$H101*$F101
B102: 45355 | C102: 3 | D102: Airplane Ticket PLM-CGK | F102: 1119500 | G102: IDR | H102: 1 | I102: =$H102*$F102
D103: Transportation
...

Sheet Laba rugi -2024
B3: PT. EXSPAN WIRELINE INDONESIA | G3: PT. EXSPAN WIRELINE INDONESIA
B4: LABA RUGI | TAHUN 2024 | G4: NERACA |TAHUN YANG BERAKHIR, 31 DESEMBER 2024
D6: PT. Exspan Wireline Indonesia | I6: PT. Exspan Wireline Indonesia
D7: (Rp) | I7: (Rp)
B8: PENDAPATAN | G8: AKTIVA
C9: PENDAPATAN LANGSUNG | D9: Rp | E9: =SUM('Revenue-Cost_2024'!F8:F20) | G9: AKTIVA LANCAR
C10: PENDAPATAN LAIN LAIN | D10: Rp | E10: =SUM('Revenue-Cost_2024'!F21) | H10: KAS DAN SETARA KAS TAHUN SEBELUMNYA | I10: Rp | J10: =161401093
H11: KAS DAN SETARA KAS TAHUN LAPORAN | I11: Rp | J11: =E46-'Business Summary'!E13
B12: TOTALPENDAPATAN | D12: Rp | E12: =SUM(E9:E11) | H12: PIUTANG USAHA | I12: Rp | J12: 0
H13: PAJAK BAYAR DI MUKA (pph23) | I13: Rp | J13: 0
B14: BEBAN LANGSUNG | H14: BIAYA BAYAR DI MUKA | I14: Rp | J14: 0
C15: Biaya Operasi | D15: Rp | E15: ='Revenue-Cost_2024'!I750 | H15: PIUTANG LAIN LAIN | I15: Rp | J15: 0
C16: Biaya research (R & D) | D16: Rp | E16: ='Revenue-Cost_2024'!J750 | H16: TOTAL AKTIVA LANCAR | I16: Rp | J16: =SUM(J10:J14)
C17: BIAYA SEWA PERALATAN | D17: Rp | E17: ='Revenue-Cost_2024'!K750
C18: BIAYA Data Processing | D18: Rp | E18: ='Revenue-Cost_2024'!L750 | G18: ACTIVA TETAP
H20: INVENTARIS KANTOR | I20: Rp | J20: 0
B21: TOTAL BIAYA LANGSUNG | D21: Rp | E21: =SUM(E15:E20)
H22: TOTAL AKTIVA TETAP | I22: Rp | J22: =J20
B23: BEBAN TIDAK LANGSUNG | E23: ='Revenue-Cost_2024'!Q750
G24: ACTIVA LAIN LAIN | J24: 0
D25: Rp
H26: TOTAL AKTIVA LAIN LAIN | I26: Rp | J26: =SUM(J25:J25)
B27: TOTAL BIAYA TIDAK LANGSUNG | D27: Rp | E27: =SUM(E22:E26)
G28: TOTAL AKTIVA | I28: Rp | J28: =J26+J22+J16
B29: BIAYA ADMINISTRASI DAN UMUM
C30: BIAYA ADMINISTRASI | D30: Rp | E30: ='Revenue-Cost_2024'!M750 | G30: HUTANG DAN MODAL
C31: BIAYA PEMBELIAN Barang | D31: Rp | E31: ='Revenue-Cost_2024'!N750
C32: BIAYA SEWA KANTOR | D32: Rp | E32: ='Revenue-Cost_2024'!O750 | G32: HUTANG LANCAR
C33: BIAYA KESEHATAN | D33: Rp | E33: ='Revenue-Cost_2024'!P750 | H33: HUTANG USAHA | I33: Rp | J33: 0
H34: HUTANG GAJI | I34: Rp | J34: 0
B35: TOTAL BIAYA ADMINISTRASI DAN UMUM | D35: Rp | E35: =SUM(E30:E34) | H35: HUTANG PEMEGANG SAHAM | I35: Rp | J35: 0
H36: BIAYA YANG MASIH HARUS DI BAYAR | I36: Rp | J36: 0
B37: TOTAL BIAYA | D37: Rp | E37: =E35+E21+E27
H38: TOTAL HUTANG LANCAR | J38: =SUM(J33:J36)
B39: PENDAPATAN/BEBAN LAIN LAIN | D39: Rp
C40: PENDAPATAN LAINNYA | D40: Rp | E40: 0 | G40: MODAL
H41: MODAL SAHAM | I41: Rp | J41: 0
B42: LABA RUGI SEBELUM PAJAK | D42: Rp | E42: =E12-E37 | H42: LABA DI TAHAN | I42: Rp | J42: 0
H43: TOTAL LABA (RUGI) DITAHAN | I43: Rp | J43: =J28
B44: CORPORATE TAX (PPh 29) | D44: Rp | E44: 0.1 | H44: TOTAL MODAL | I44: Rp | J44: =SUM(J41:J43)
B46: LABA / RUGI BERSIH | E46: =E42-E44 | G46: TOTAL HUTANG DAN MODAL | I46: Rp | J46: =J44+J38
B49: Anevril Chairulsyah | G49: Anevril Chairulsyah
B50: Direktur | G50: Direktur

Sheet Business Summary
B3: PT. EXSPAN WIRELINE INDONESIA
B4: BUSINESS SUMMARY | TAHUN 2024
B6: # | C6: Items | D6: Amount
B7: 1 | C7: Revenue | D7: Rp | E7: ='Revenue-Cost_2024'!F22
B8: 2 | C8: Revenue Diterima (Setelah Pajak) | D8: Rp | E8: =E7-'Revenue-Cost_2024'!N22
B9: 3 | C9: Biaya | D9: Rp | E9: =SUM('Revenue-Cost_2024'!I750:Q750)
B10: 4 | C10: Profit SebelumTax | D10: Rp | E10: =E7-E9
B11: 5 | C11: PPh Badan (22%*50%) | D11: Rp | E11: =E10*22%*50%
B12: 6 | C12: PPh 23 Dipotong oleh client | D12: Rp | E12: ='Revenue-Cost_2024'!N22
B13: 7 | C13: Kekurangan Bayar PPh Badan | D13: Rp | E13: =E11-E12
B14: 8 | C14: Profit After Tax | D14: Rp | E14: =E10-E13
B15: 9 | C15: Deviden Dibagi | D15: Rp | E15: 858000000
B16: 10 | C16: Profit Ditahan | D16: Rp | E16: =E14-E15
B18: DEVIDEN
B19: 1 | C19: Alan Muhadjir | D19: Rp | E19: =E15/2 | G19: Pajak 10%
B20: 2 | C20: Anevril Chairulsyah | D20: Rp | E20: =E15/2 | G20: Pajak 10%
