Workbook

Sheet Revenue-Cost_2024
B1: Daily Report - Balance Calculation Operation Cost
B2: Project | C2: : | D2: REVENUE vs OPERATION COST Tahun 2024
B3: Date | C3: : | D3: Januari - Desember 2024
B5: REVENUE & TAX
B6: Invoice Date | C6: # | D6: Detail/Description | F6: INVOICE VALUE | G6: Currency | H6: Currency Exchange | I6: INVOICE Number | J6: Client | K6: Receive Date | L6: AMOUNT RECEIVED | M6: PPn | N6: PPH (Pasal 23) | O6: Biaya transfer | P6: Remark
L7: IDR | M7: 0.11 | N7: 0.02
B8: 45302 | C8: 2 | D8: ALFA Service PDP-075 Pertamina Zona#4 | F8: 354210000 | G8: IDR | H8: 1 | I8: INV017 | J8: SI Jak | K8: 45350 | L8: 347125800 | M8: =(F8*11%) | N8: =(F8*2%) | O8: =F8-N8-L8 | P8: Pemungut
B9: 45301 | C9: 3 | D9: Revenue data procesing MTD_Tomori | F9: 150000000 | G9: IDR | H9: 1 | I9: INV015 | J9: TGE | K9: 45399 | L9: 166500000 | M9: =(F9*11%) | N9: =(F9*2%) | O9: 0 | Q9: inc.PPN11%
B10: 45302 | C10: 4 | D10: ALFA Service PDS-01ST Pertamina Zona#4 | F10: 354210000 | G10: IDR | H10: 1 | I10: INV019 | J10: SI Jak | K10: 45425 | L10: 347125800 | M10: =(F10*11%) | N10: =(F10*2%) | O10: =F10-N10-L10 | P10: Pemungut
B11: 45302 | C11: 5 | D11: ALFA Service JRK-254 Pertamina Zona#4 | F11: 354210000 | G11: IDR | H11: 1 | I11: INV018 | J11: SI Jak | K11: 45453 | L11: 347125800 | M11: =(F11*11%) | N11: =(F11*2%) | O11: =F11-N11-L11 | P11: Pemungut
B12: 45446 | C12: 6 | D12: ALFA Service TLJ-58 Pertamina Zona#4 | F12: 354210000 | G12: IDR | H12: 1 | I12: INV020 | J12: SI Jak | K12: 45497 | L12: 347125800 | M12: =(F12*11%) | N12: =(F12*2%) | O12: =F12-N12-L12 | P12: Pemungut
B13: 45447 | C13: 7 | D13: ALFA Service JRK-193 Pertamina Zona#4 | F13: 354210000 | G13: IDR | H13: 1 | I13: INV021 | J13: SI Jak | K13: 45516 | L13: 347125800 | M13: =(F13*11%) | N13: =(F13*2%) | O13: =F13-N13-L13 | P13: Pemungut
B14: 45539 | C14: 8 | D14: Revenue Repair Electric Assisted Stimulation Machine (no 23) | F14: 89000000 | G14: IDR | H14: 1 | I14: INV023 | J14: LBU | K14: 45553 | L14: =(89000000*98%)+9700000 | M14: =(F14*11%) | N14: =(F14*2%) | Q14: inc.PPN11%
B15: 45537 | C15: 9 | D15: ALFA Service JRK-163 Pertamina Zona#4 | F15: 354210000 | G15: IDR | H15: 1 | I15: INV022 | J15: SI Jak | K15: 45575 | L15: 347125800 | M15: =(F15*11%) | N15: =(F15*2%) | O15: =F15-N15-L15 | P15: Pemungut
B16: 45576 | C16: 10 | D16: Revenue Project TIS (no 28 ) | F16: 819200000 | G16: IDR | H16: 1 | I16: INV028 | J16: Barikin Sakti | K16: 45579 | L16: 892928000 | M16: =(F16*11%) | N16: =(F16*2%) | O16: =L16-(F16+M16-N16) | Q16: inc.PPN11%
B17: 45572 | C17: 11 | D17: ALFA Service JRK-095 Pertamina Zona#4 | F17: 354210000 | G17: IDR | H17: 1 | I17: INV027 | J17: SI Jak | K17: 45607 | L17: 347125800 | M17: =(F17*11%) | N17: =(F17*2%) | O17: =F17-N17-L17 | P17: Pemungut
B18: 45569 | C18: 12 | D18: ALFA Service TGB-033 Pertamina Cirebon | F18: 290000000 | G18: IDR | H18: 1 | I18: INV024 | J18: Elnusa | K18: 45646 | L18: 284197100 | M18: =(F18*11%) | N18: =(F18*2%) | O18: =F18-N18-L18 | P18: Pemungut
B19: 45569 | C19: 13 | D19: MFC Service TGB-033 Pertamina Cirebon | F19: 280000000 | G19: IDR | H19: 1 | I19: INV025 | J19: Elnusa | K19: 45653 | L19: 412577100 | M19: =(F19*11%) | N19: =(F19*2%) | O19: =F19+F20-L19-(N19+N20) | P19: Pemungut
B20: 45569 | C20: 14 | D20: PLT Service TGB-033 Pertamina Cirebon | F20: 141000000 | G20: IDR | H20: 1 | I20: INV026 | J20: Elnusa | M20: =(F20*11%) | N20: =(F20*2%) | P20: Pemungut
B21: 45657 | C21: 15 | D21: Bunga Bank 2024 | F21: 6925425 | G21: IDR | L21: =F21
B22: REVENUE (IDR) | F22: 4289928225 | L22: =SUM(L8:L21) | M22: =SUM(M8:M21) | N22: 84973400
B24: PAJAK PENGELUARAN
B25: Date | C25: # | D25: Detail/Description | F25: Transaction Value | G25: Currency | H25: Currency Exchange | I25: PPN | K25: PPh (pasal 21) | M25: PPh (pasal 23) | O25: PPh (pasal 26)
I26: Transaction | J26: PPN | K26: Transaction | L26: PPh - 21 | M26: Transaction | N26: PPh - 23 | O26: Transaction | P26: PPh - 26
B27: 45289 | D27: Tax PPN 11% (Project TGE MEPI Rimau Pembayaran Ke-2) | F27: 33836000 | J27: 33836000
B28: 45302 | D28: Tax PPN 11% (Project TGE MEPI Rimau Pembayaran Ke-2) | F28: 33836000 | J28: 33836000
B29: 45351 | D29: Tax PPN 11% (Project TGE MEPI Tomori) | F29: 16500000 | J29: 16500000
B30: 45567 | D30: Tax PPN 11% (Perbaikan Repair Electric Assisted Stimulation Machine) | F30: 9790000 | J30: 9790000
B31: 45546 | D31: Pinalty Telat bayar pajak PP21 Sewa tool ALFA 2023 | F31: 25439666 | L31: 25439666
B32: 45546 | D32: Tax PPN 11% pajak Inv-007 tahun 2023 sarulla project - Sibat | F32: 96126126 | J32: 97126126
B33: 45589 | D33: Penalty telat bayar pajak PPN project sarulla_INV-007_under Sibat | F33: 17716045
B34: 45593 | D34: Pemindahbukan dari double bayar (29 des 2023) utk PPN Inv-028 | F34: 33836000 | J34: 33836000
B35: 45607 | D35: Kekurangan pajak PPn Inv-028 (barikikn Sakti)(1/3 nya dari PBK pajak) | F35: 56276000 | J35: 56276000
B36: 45607 | D36: Kekurangan pajak final PPH 23 keuntungan perusahaan tahun 2023 | F36: 1726469 | N36: 1726469
B37: PENERIMAAN NEGARA (TAX) (IDR) | I37: PPN | J37: 281200126 | K37: PPh | L37: 25439666 | M37: PPh | N37: 1726469 | O37: PPh | P37: 0 | Q37: -
B39: PENGELUARAN
B40: Date | C40: # | D40: Activity | E40: Source | F40: Jumlah | G40: Currency | H40: urrency Exchange | I40: Biaya Research (R&D) | J40: Biaya Operasi | K40: Biaya Sewa Peralatan | L40: Biaya Interpretasi Log Data | M40: Administrasi | N40: Pembelian Barang | O40: Sewa Kantor | P40: Kesehatan | Q40: Bisnis Dev | R40: asdasd | S40: makanan jepang | T40: aaaaa | U40: bbbbb | V40: asdsad | W40: dfgdfgdfgd | X40: 12312
D41: Allowance
B42: 45388 | C42: 1 | D42: THR 2024_Yufitri | E42: BCA | F42: 3000000 | G42: IDR | H42: 1 | J42: 3000000
D43: Biaya Bank
B44: 45657 | C44: 2 | D44: Total Biaya Transaksi Bank selama 1 tahun | E44: - | F44: 1998587 | G44: IDR | H44: 1 | M44: 1998587
D45: Biaya Interpretasi Log Data
B46: 45413 | C46: 3 | D46: Data proccesing MTD 4 well, project Tomori-Alan | E46: BCA | F46: 122625000 | G46: IDR | H46: 1 | L46: 122625000
B47: 45525 | C47: 4 | D47: Data proccesing TGB-33 DAN TIS (RBG-3b)-Alan | E47: BCA | F47: 101120000 | G47: IDR | H47: 1 | L47: 101120000
D48: Biaya Operasi
B49: 45446 | C49: 5 | D49: PT Laka Indonesia | Wastafel for WIKA Anantara Ubud Bali | E49: BCA | F49: 300000000 | G49: IDR | H49: 1 | J49: 300000000
B50: 45480 | C50: 6 | D50: PT Laka Indonesia | Wastafel for WIKA Anantara Ubud Bali | E50: BCA | F50: 25000000 | G50: IDR | H50: 1 | J50: 25000000
B51: 45492 | C51: 7 | D51: PT Laka Indonesia | Wastafel for WIKA Anantara Ubud Bali | E51: BCA | F51: 25000000 | G51: IDR | H51: 1 | J51: 25000000
D52: Biaya Research (R&D)
B53: 45364 | C53: 8 | D53: Ralika Jaya Utama | Permbuatan alat Downhole Wireless Telemetry | E53: BCA | F53: 100000000 | G53: IDR | H53: 1 | I53: 100000000
B54: 45418 | C54: 9 | D54: Ralika Jaya Utama | Permbuatan alat Downhole Wireless Telemetry | E54: BRI | F54: 100000000 | G54: IDR | H54: 1 | I54: 100000000
B55: 45502 | C55: 10 | D55: Ralika Jaya Utama | Permbuatan alat injeksi listrik (EAS) | E55: BRI | F55: 100000000 | G55: IDR | H55: 1 | I55: 100000000
B56: 45548 | C56: 11 | D56: Ralika Jaya Utama | Permbuatan alat EMR | E56: BRI | F56: 150000000 | G56: IDR | H56: 1 | I56: 150000000
B57: 45631 | C57: 12 | D57: Ralika Jaya Utama | Permbuatan alat injeksi listrik (EAS) | E57: BRI | F57: 400000000 | G57: IDR | H57: 1 | I57: 400000000
D58: Bisnis Dev
B59: 45483 | C59: 13 | D59: Pembelian Lisence Sonoechometer to PT Weebz Mandiri | E59: BCA | F59: 16650000 | G59: IDR | H59: 1 | Q59: 16650000
B60: 45539 | C60: 14 | D60: MUTRI | Penambahan modal biaya kerja | E60: BRI | F60: 100000000 | G60: IDR | H60: 1 | Q60: 100000000
B61: 45625 | C61: 15 | D61: MUTRI | Penambahan modal biaya kerja 3rd | E61: BRI | F61: 75000000 | G61: IDR | H61: 1 | Q61: 75000000
D62: Data Processing
B63: 45589 | C63: 16 | D63: Data Processing 8 Well Alan Project SIJAK | E63: BRI | F63: 144000000 | G63: IDR | H63: 1 | L63: 144000000
D64: Gaji
B65: 45323 | C65: 17 | D65: Gaji Januari 2024 _Yufitri | E65: BCA | F65: 2500000 | G65: IDR | H65: 1 | J65: 2500000
B66: 45356 | C66: 18 | D66: Gaji Februari 2024 + raple gaji Januari 2024_Yufitri | E66: BCA | F66: 3500000 | G66: IDR | H66: 1 | J66: 3500000
B67: 45379 | C67: 19 | D67: Gaji Maret 2024_Yufitri | E67: BCA | F67: 3000000 | G67: IDR | H67: 1 | J67: 3000000
B68: 45416 | C68: 20 | D68: Gaji April_Yufitri | E68: BCA | F68: 3000000 | G68: IDR | H68: 1 | J68: 3000000
B69: 45446 | C69: 21 | D69: Gaji Mei_Yufitri | E69: BCA | F69: 3000000 | G69: IDR | H69: 1 | J69: 3000000
B70: 45473 | C70: 22 | D70: Gaji Juni 2024_Yufitri | E70: BCA | F70: 3000000 | G70: IDR | H70: 1 | J70: 3000000
B71: 45501 | C71: 23 | D71: Gaji Juli 2024_Yufitri | E71: BCA | F71: 3000000 | G71: IDR | H71: 1 | J71: 3000000
B72: 45535 | C72: 24 | D72: Gaji Agustus 2024_Yufitri | E72: BCA | F72: 3000000 | G72: IDR | H72: 1 | J72: 3000000
B73: 45568 | C73: 25 | D73: Gaji fitri bulan september 2024 | E73: BRI | F73: 3000000 | G73: IDR | H73: 1 | J73: 3000000
B74: 45568 | C74: 26 | D74: Gaji fitri bulan October 2024 | E74: BRI | F74: 3000000 | G74: IDR | H74: 1 | J74: 3000000
B75: 45625 | C75: 27 | D75: Gaji fitri bulan November 2024 | E75: BRI | F75: 3000000 | G75: IDR | H75: 1 | J75: 3000000
B76: 45651 | C76: 28 | D76: Gaji Desember 2024 + Bomnus akhir tahun - 4 bulan_Yufitri | E76: BCA | F76: 15000000 | G76: IDR | H76: 1 | J76: 15000000
D77: Maintenance
B78: 45478 | C78: 29 | D78: Repair ESOR panel & Fabricate dummy test load, Payment#2 | E78: BRI | F78: 25000000 | G78: IDR | H78: 1 | J78: 25000000
B79: 45493 | C79: 30 | D79: Repair ESOR panel & Fabricate dummy test load, Payment#1 | E79: BCA | F79: 20000000 | G79: IDR | H79: 1 | J79: 20000000
D80: Operation
B81: 45501 | C81: 31 | D81: Handphone Operational untuk Secretary (Yufitri) | E81: BCA | F81: 2600000 | G81: IDR | H81: 1 | N81: 2600000
D82: Pembelian Barang
B83: 45476 | C83: 32 | D83: Kekurangan (PPN ) ke PT Garindo sarana Baru (Downhole Sampling) | E83: BCA | F83: 3582000 | G83: IDR | H83: 1 | N83: 3582000
D84: Pembuatan Alat
B85: 45653 | C85: 33 | D85: KUPA | Pembelian Mesin Retort Horizontal 500 Lt Automatic Control | E85: BCA | F85: 141500000 | G85: IDR | H85: 1 | I85: 141500000
D86: Project Operation
B87: 45422 | C87: 34 | D87: Aro Energy | Moving slickline dari Duri (Toni Supriadi) ke Sungai lilin | E87: BCA | F87: 18000000 | G87: IDR | H87: 1 | J87: 18000000
B88: 45581 | C88: 35 | D88: PT Laka Indonesia | Project Lampu Taman Istana Negara Jakarta | E88: BRI | F88: 100000000 | G88: IDR | H88: 1 | J88: 100000000
D89: Rental Tool
B90: 45302 | C90: 36 | D90: ALFA Service PDP-075 Pertamina Zona#4 - Rental Tool | E90: BCA | F90: 29640916 | G90: IDR | H90: 1 | K90: 29640916
B91: 45302 | C91: 37 | D91: ALFA Service PDS-01ST Pertamina Zona#4 - Rental Tool | E91: BCA | F91: 29640916 | G91: IDR | H91: 1 | K91: 29640916
B92: 45302 | C92: 38 | D92: ALFA Service JRK-254 Pertamina Zona#4 - Rental Tool | E92: BCA | F92: 29640916 | G92: IDR | H92: 1 | K92: 29640916
B93: 45446 | C93: 39 | D93: ALFA Service TLJ-58 Pertamina Zona#4 - Rental Tool | E93: BCA | F93: 29640916 | G93: IDR | H93: 1 | K93: 29640916
B94: 45447 | C94: 40 | D94: ALFA Service JRK-193 Pertamina Zona#4 - Rental Tool | E94: BCA | F94: 29640916 | G94: IDR | H94: 1 | K94: 29640916
B95: 45537 | C95: 41 | D95: ALFA Service JRK-163 Pertamina Zona#4 - Rental Tool | E95: BCA | F95: 29640916 | G95: IDR | H95: 1 | K95: 29640916
B96: 45569 | C96: 42 | D96: PLT Service TGB-033 Pertamina Cirebon - Rental Tool | E96: BCA | F96: 16165271 | G96: IDR | H96: 1 | K96: 16165271
B97: 45569 | C97: 43 | D97: ALFA Service TGB-033 Pertamina Cirebon - Rental Tool | E97: BCA | F97: 25967616 | G97: IDR | H97: 1 | K97: 25967616
B98: 45569 | C98: 44 | D98: MFC Service TGB-033 Pertamina Cirebon - Rental Tool | E98: BCA | F98: 32101247 | G98: IDR | H98: 1 | K98: 32101247
B99: 45572 | C99: 45 | D99: ALFA Service JRK-095 Pertamina Zona#4 - Rental Tool | E99: BCA | F99: 29640916 | G99: IDR | H99: 1 | K99: 29640916
B100: 45576 | C100: 46 | D100: MPLT/GR-CCL/ALFA TIS - Rental Tool | E100: BCA | F100: 74291457 | G100: IDR | H100: 1 | K100: 74291457
D101: Sales
B102: 45304 | C102: 47 | D102: Sales cost 4 Well Integrity Pertamina Z.4 | E102: BRI | F102: 77672400 | G102: IDR | H102: 1 | J102: 77672400
B103: 45601 | C103: 48 | D103: Sales fee 2 Well Integrity Pertamina Z.4 | E103: BRI | F103: 38838700 | G103: IDR | H103: 1 | J103: 38838700
...

Sheet Laba rugi -2024
B3: PT. EXSPAN WIRELINE INDONESIA | G3: PT. EXSPAN WIRELINE INDONESIA
B4: LABA RUGI | TAHUN 2024 | G4: NERACA | TAHUN YANG BERAKHIR, 31 DESEMBER 2024 | K4: CATATAN KEAMANAN
K5: Kolom ini aman dari overwrite sistem.
D6: PT. Exspan Wireline Indonesia | I6: PT. Exspan Wireline Indonesia | K6: Diverifikasi pada: 2026-03-29 15:30
D7: (Rp) | I7: (Rp)
B8: PENDAPATAN | G8: AKTIVA
C9: PENDAPATAN LANGSUNG | D9: Rp | E9: =SUM('Revenue-Cost_2024'!F8:F20) | G9: AKTIVA LANCAR
C10: PENDAPATAN LAIN LAIN | D10: Rp | E10: =SUM('Revenue-Cost_2024'!F21) | H10: KAS DAN SETARA KAS TAHUN SEBELUMNYA | I10: Rp | J10: 0
H11: KAS DAN SETARA KAS TAHUN LAPORAN | I11: Rp | J11: =E46-'Business Summary'!E13
B12: TOTALPENDAPATAN | D12: Rp | E12: =SUM(E9:E11) | H12: PIUTANG USAHA | I12: Rp | J12: 0
H13: PAJAK BAYAR DI MUKA (pph23) | I13: Rp | J13: 0
B14: BEBAN LANGSUNG | H14: BIAYA BAYAR DI MUKA | I14: Rp | J14: 0
C15: Biaya Operasi | D15: Rp | E15: ='Revenue-Cost_2024'!I750 | H15: PIUTANG LAIN LAIN | I15: Rp | J15: 0
C16: Biaya research (R & D) | D16: Rp | E16: ='Revenue-Cost_2024'!J750 | H16: TOTAL AKTIVA LANCAR | I16: Rp | J16: =SUM(J10:J15)
C17: BIAYA SEWA PERALATAN | D17: Rp | E17: ='Revenue-Cost_2024'!K750
C18: BIAYA Data Processing | D18: Rp | E18: ='Revenue-Cost_2024'!L750 | G18: ACTIVA TETAP
H20: INVENTARIS KANTOR | I20: Rp | J20: 0
B21: TOTAL BIAYA LANGSUNG | D21: Rp | E21: =SUM(E15:E20)
H22: TOTAL AKTIVA TETAP | I22: Rp | J22: =J20
B23: BEBAN TIDAK LANGSUNG | E23: ='Revenue-Cost_2024'!Q750
G24: ACTIVA LAIN LAIN | J24: 0
D25: Rp | J25: 0
H26: TOTAL AKTIVA LAIN LAIN | I26: Rp | J26: =SUM(J25:J25)
B27: TOTAL BIAYA TIDAK LANGSUNG | D27: Rp | E27: =SUM(E22:E26)
G28: TOTAL AKTIVA | I28: Rp | J28: =J26+J22+J16
B29: BIAYA ADMINISTRASI DAN UMUM
C30: BIAYA ADMINISTRASI | D30: Rp | E30: ='Revenue-Cost_2024'!M750 | G30: HUTANG DAN MODAL
C31: BIAYA PEMBELIAN Barang | D31: Rp | E31: ='Revenue-Cost_2024'!N750
C32: BIAYA SEWA KANTOR | D32: Rp | E32: ='Revenue-Cost_2024'!O750 | G32: HUTANG LANCAR
C33: BIAYA KESEHATAN | D33: Rp | E33: ='Revenue-Cost_2024'!P750 | H33: HUTANG USAHA | I33: Rp | J33: 0
H34: HUTANG GAJI | I34: Rp | J34: 0
B35: TOTAL BIAYA ADMINISTRASI DAN UMUM | D35: Rp | E35: =SUM(E30:E34) | H35: HUTANG PEMEGANG SAHAM | I35: Rp | J35: 0
H36: BIAYA YANG MASIH HARUS DI BAYAR | I36: Rp | J36: 0
B37: TOTAL BIAYA | D37: Rp | E37: =E35+E21+E27
H38: TOTAL HUTANG LANCAR | J38: =SUM(J33:J36)
B39: PENDAPATAN/BEBAN LAIN LAIN | D39: Rp
C40: PENDAPATAN LAINNYA | D40: Rp | E40: 0 | G40: MODAL
H41: MODAL SAHAM | I41: Rp | J41: 0
B42: LABA RUGI SEBELUM PAJAK | D42: Rp | E42: =E12-E37 | H42: LABA DI TAHAN | I42: Rp | J42: 0
H43: TOTAL LABA (RUGI) DITAHAN | I43: Rp | J43: =J28-J38-J41-J42
B44: CORPORATE TAX (PPh 29) | D44: Rp | E44: 0 | H44: TOTAL MODAL | I44: Rp | J44: =SUM(J41:J43)
B46: LABA / RUGI BERSIH | E46: =E42-E44 | G46: TOTAL HUTANG DAN MODAL | I46: Rp | J46: =J44+J38
B50: Direktur | G50: Direktur

Sheet Business Summary
B3: PT. EXSPAN WIRELINE INDONESIA
B4: BUSINESS SUMMARY | TAHUN 2024
B6: # | C6: Items | D6: Amount
B7: 1 | C7: Revenue | D7: Rp | E7: ='Revenue-Cost_2024'!F22
B8: 2 | C8: Revenue Diterima (Setelah Pajak) | D8: Rp | E8: =E7-'Revenue-Cost_2024'!N22
B9: 3 | C9: Biaya | D9: Rp | E9: =SUM('Revenue-Cost_2024'!I750:Q750)
B10: 4 | C10: Profit SebelumTax | D10: Rp | E10: =E7-E9
B11: 5 | C11: PPh Badan (22%*50%) | D11: Rp | E11: =E10*22%*50%
B12: 6 | C12: PPh 23 Dipotong oleh client | D12: Rp | E12: ='Revenue-Cost_2024'!N22
B13: 7 | C13: Kekurangan Bayar PPh Badan | D13: Rp | E13: =E11-E12
B14: 8 | C14: Profit After Tax | D14: Rp | E14: =E10-E13
B15: 9 | C15: Deviden Dibagi | D15: Rp | E15: =E14-E16
B16: 10 | C16: Profit Ditahan | D16: Rp | E16: 33763737
B18: DEVIDEN
A19: 1 | B19: Anevril Chairulsyah | D19: Rp | E19: =IF(B19="","",$E$15/COUNTA($B$19:$B$79)) | G19: Pajak 10%
A20: 2 | B20: Alan Muhadjir | D20: Rp | E20: =IF(B20="","",$E$15/COUNTA($B$19:$B$79)) | G20: Pajak 10%
