Workbook

Sheet Revenue-Cost_2024
B1: Daily Report - Balance Calculation Operation Cost
B2: Project | C2: : | D2: REVENUE vs OPERATION COST Tahun 2024
B3: Date | C3: : | D3: Januari - Desember 2024
B5: REVENUE & TAX
B6: Invoice Date | C6: # | D6: Detail/Description | F6: INVOICE VALUE | G6: Currency | H6: Currency Exchange | I6: INVOICE Number | J6: Client | K6: Receive Date | L6: AMOUNT RECEIVED | M6: PPn | N6: PPH (Pasal 23) | O6: Biaya transfer | P6: Remark
L7: IDR | M7: 0.11 | N7: 0.02 | Q7: con: inc.PPN11%
B8: 45302 | C8: 1 | D8: ALFA Service PDP-075 Pertamina Zona#4 | F8: 354210000 | G8: IDR | H8: 1 | I8: INV017 | J8: SI Jak | K8: 45350 | L8: 347125800 | M8: 38963100 | N8: 7084200 | O8: 0 | P8: Pemungut
B9: 45302 | C9: 2 | D9: ALFA Service PDP-075 Pertamina Zona#4 | F9: 354210000 | G9: IDR | H9: 1 | I9: INV017 | J9: SI Jak | K9: 45350 | L9: 347125800 | M9: 38963100 | N9: 7084200 | O9: 0 | P9: Pemungut
B10: 45302 | C10: 3 | D10: ALFA Service PDP-075 Pertamina Zona#4 | F10: 354210000 | G10: IDR | H10: 1 | I10: INV017 | J10: SI Jak | K10: 45350 | L10: 347125800 | M10: 38963100 | N10: 7084200 | O10: 0 | P10: Pemungut
B11: 45302 | C11: 4 | D11: ALFA Service PDP-075 Pertamina Zona#4 | F11: 354210000 | G11: IDR | H11: 1 | I11: INV017 | J11: SI Jak | K11: 45350 | L11: 347125800 | M11: 38963100 | N11: 7084200 | O11: 0 | P11: Pemungut
B12: 45302 | C12: 5 | D12: ALFA Service PDP-075 Pertamina Zona#4 | F12: 354210000 | G12: IDR | H12: 1 | I12: INV017 | J12: SI Jak | K12: 45350 | L12: 347125800 | M12: 38963100 | N12: 7084200 | O12: 0 | P12: Pemungut
B13: 45302 | C13: 6 | D13: ALFA Service PDP-075 Pertamina Zona#4 | F13: 354210000 | G13: IDR | H13: 1 | I13: INV017 | J13: SI Jak | K13: 45350 | L13: 347125800 | M13: 38963100 | N13: 7084200 | O13: 0 | P13: Pemungut
B14: 45302 | C14: 7 | D14: ALFA Service PDP-075 Pertamina Zona#4 | F14: 354210000 | G14: IDR | H14: 1 | I14: INV017 | J14: SI Jak | K14: 45350 | L14: 347125800 | M14: 38963100 | N14: 7084200 | O14: 0 | P14: Pemungut
B15: 45302 | C15: 8 | D15: ALFA Service PDP-075 Pertamina Zona#4 | F15: 354210000 | G15: IDR | H15: 1 | I15: INV017 | J15: SI Jak | K15: 45350 | L15: 347125800 | M15: 38963100 | N15: 7084200 | O15: 0 | P15: Pemungut
B16: 45302 | C16: 9 | D16: ALFA Service PDP-075 Pertamina Zona#4 | F16: 354210000 | G16: IDR | H16: 1 | I16: INV017 | J16: SI Jak | K16: 45350 | L16: 347125800 | M16: 38963100 | N16: 7084200 | O16: 0 | P16: Pemungut
B17: 45302 | C17: 10 | D17: ALFA Service PDP-075 Pertamina Zona#4 | F17: 354210000 | G17: IDR | H17: 1 | I17: INV017 | J17: SI Jak | K17: 45350 | L17: 347125800 | M17: 38963100 | N17: 7084200 | O17: 0 | P17: Pemungut
B18: 45302 | C18: 11 | D18: ALFA Service PDP-075 Pertamina Zona#4 | F18: 354210000 | G18: IDR | H18: 1 | I18: INV017 | J18: SI Jak | K18: 45350 | L18: 347125800 | M18: 38963100 | N18: 7084200 | O18: 0 | P18: Pemungut
B19: 45302 | C19: 12 | D19: ALFA Service PDP-075 Pertamina Zona#4 | F19: 354210000 | G19: IDR | H19: 1 | I19: INV017 | J19: SI Jak | K19: 45350 | L19: 347125800 | M19: 38963100 | N19: 7084200 | O19: 0 | P19: Pemungut
... B28: 45302 | C28: 21 | D28: ALFA Service PDP-075 Pertamina Zona#4 | F28: 354210000 | G28: IDR | H28: 1 | I28: INV017 | J28: SI Jak | K28: 45350 | L28: 347125800 | M28: 38963100 | N28: 7084200 | O28: 0 | P28: Pemungut
B29: 45301 | C29: 22 | D29: Revenue data procesing MTD_Tomori | F29: 150000000 | G29: IDR | H29: 1 | I29: INV015 | J29: TGE | K29: 45399 | L29: 166500000 | M29: 16500000 | N29: 3000000 | O29: 0
B30: 45301 | C30: 23 | D30: Revenue data procesing MTD_Tomori | F30: 150000000 | G30: IDR | H30: 1 | I30: INV015 | J30: TGE | K30: 45399 | L30: 166500000 | M30: 16500000 | N30: 3000000 | O30: 0
B31: 45301 | C31: 24 | D31: Revenue data procesing MTD_Tomori | F31: 150000000 | G31: IDR | H31: 1 | I31: INV015 | J31: TGE | K31: 45399 | L31: 166500000 | M31: 16500000 | N31: 3000000 | O31: 0
B32: 45301 | C32: 25 | D32: Revenue data procesing MTD_Tomori | F32: 150000000 | G32: IDR | H32: 1 | I32: INV015 | J32: TGE | K32: 45399 | L32: 166500000 | M32: 16500000 | N32: 3000000 | O32: 0
B33: 45301 | C33: 26 | D33: Revenue data procesing MTD_Tomori | F33: 150000000 | G33: IDR | H33: 1 | I33: INV015 | J33: TGE | K33: 45399 | L33: 166500000 | M33: 16500000 | N33: 3000000 | O33: 0
B34: 45301 | C34: 27 | D34: Revenue data procesing MTD_Tomori | F34: 150000000 | G34: IDR | H34: 1 | I34: INV015 | J34: TGE | K34: 45399 | L34: 166500000 | M34: 16500000 | N34: 3000000 | O34: 0
B35: 45301 | C35: 28 | D35: Revenue data procesing MTD_Tomori | F35: 150000000 | G35: IDR | H35: 1 | I35: INV015 | J35: TGE | K35: 45399 | L35: 166500000 | M35: 16500000 | N35: 3000000 | O35: 0
B36: 45301 | C36: 29 | D36: Revenue data procesing MTD_Tomori | F36: 150000000 | G36: IDR | H36: 1 | I36: INV015 | J36: TGE | K36: 45399 | L36: 166500000 | M36: 16500000 | N36: 3000000 | O36: 0
B37: 45301 | C37: 30 | D37: Revenue data procesing MTD_Tomori | F37: 150000000 | G37: IDR | H37: 1 | I37: INV015 | J37: TGE | K37: 45399 | L37: 166500000 | M37: 16500000 | N37: 3000000 | O37: 0
B38: 45301 | C38: 31 | D38: Revenue data procesing MTD_Tomori | F38: 150000000 | G38: IDR | H38: 1 | I38: INV015 | J38: TGE | K38: 45399 | L38: 166500000 | M38: 16500000 | N38: 3000000 | O38: 0
B39: 45301 | C39: 32 | D39: Revenue data procesing MTD_Tomori | F39: 150000000 | G39: IDR | H39: 1 | I39: INV015 | J39: TGE | K39: 45399 | L39: 166500000 | M39: 16500000 | N39: 3000000 | O39: 0
B40: 45301 | C40: 33 | D40: Revenue data procesing MTD_Tomori | F40: 150000000 | G40: IDR | H40: 1 | I40: INV015 | J40: TGE | K40: 45399 | L40: 166500000 | M40: 16500000 | N40: 3000000 | O40: 0
... B49: 45301 | C49: 42 | D49: Revenue data procesing MTD_Tomori | F49: 150000000 | G49: IDR | H49: 1 | I49: INV015 | J49: TGE | K49: 45399 | L49: 166500000 | M49: 16500000 | N49: 3000000 | O49: 0
B50: 45302 | C50: 43 | D50: ALFA Service PDS-01ST Pertamina Zona#4 | F50: 354210000 | G50: IDR | H50: 1 | I50: INV019 | J50: SI Jak | K50: 45425 | L50: 347125800 | M50: 38963100 | N50: 7084200 | O50: 0 | P50: Pemungut
B51: 45302 | C51: 44 | D51: ALFA Service PDS-01ST Pertamina Zona#4 | F51: 354210000 | G51: IDR | H51: 1 | I51: INV019 | J51: SI Jak | K51: 45425 | L51: 347125800 | M51: 38963100 | N51: 7084200 | O51: 0 | P51: Pemungut
B52: 45302 | C52: 45 | D52: ALFA Service PDS-01ST Pertamina Zona#4 | F52: 354210000 | G52: IDR | H52: 1 | I52: INV019 | J52: SI Jak | K52: 45425 | L52: 347125800 | M52: 38963100 | N52: 7084200 | O52: 0 | P52: Pemungut
B53: 45302 | C53: 46 | D53: ALFA Service PDS-01ST Pertamina Zona#4 | F53: 354210000 | G53: IDR | H53: 1 | I53: INV019 | J53: SI Jak | K53: 45425 | L53: 347125800 | M53: 38963100 | N53: 7084200 | O53: 0 | P53: Pemungut
B54: 45302 | C54: 47 | D54: ALFA Service PDS-01ST Pertamina Zona#4 | F54: 354210000 | G54: IDR | H54: 1 | I54: INV019 | J54: SI Jak | K54: 45425 | L54: 347125800 | M54: 38963100 | N54: 7084200 | O54: 0 | P54: Pemungut
B55: 45302 | C55: 48 | D55: ALFA Service PDS-01ST Pertamina Zona#4 | F55: 354210000 | G55: IDR | H55: 1 | I55: INV019 | J55: SI Jak | K55: 45425 | L55: 347125800 | M55: 38963100 | N55: 7084200 | O55: 0 | P55: Pemungut
B56: 45302 | C56: 49 | D56: ALFA Service PDS-01ST Pertamina Zona#4 | F56: 354210000 | G56: IDR | H56: 1 | I56: INV019 | J56: SI Jak | K56: 45425 | L56: 347125800 | M56: 38963100 | N56: 7084200 | O56: 0 | P56: Pemungut
B57: 45302 | C57: 50 | D57: ALFA Service PDS-01ST Pertamina Zona#4 | F57: 354210000 | G57: IDR | H57: 1 | I57: INV019 | J57: SI Jak | K57: 45425 | L57: 347125800 | M57: 38963100 | N57: 7084200 | O57: 0 | P57: Pemungut
B58: 45302 | C58: 51 | D58: ALFA Service PDS-01ST Pertamina Zona#4 | F58: 354210000 | G58: IDR | H58: 1 | I58: INV019 | J58: SI Jak | K58: 45425 | L58: 347125800 | M58: 38963100 | N58: 7084200 | O58: 0 | P58: Pemungut
B59: 45302 | C59: 52 | D59: ALFA Service PDS-01ST Pertamina Zona#4 | F59: 354210000 | G59: IDR | H59: 1 | I59: INV019 | J59: SI Jak | K59: 45425 | L59: 347125800 | M59: 38963100 | N59: 7084200 | O59: 0 | P59: Pemungut
B60: 45302 | C60: 53 | D60: ALFA Service PDS-01ST Pertamina Zona#4 | F60: 354210000 | G60: IDR | H60: 1 | I60: INV019 | J60: SI Jak | K60: 45425 | L60: 347125800 | M60: 38963100 | N60: 7084200 | O60: 0 | P60: Pemungut
B61: 45302 | C61: 54 | D61: ALFA Service PDS-01ST Pertamina Zona#4 | F61: 354210000 | G61: IDR | H61: 1 | I61: INV019 | J61: SI Jak | K61: 45425 | L61: 347125800 | M61: 38963100 | N61: 7084200 | O61: 0 | P61: Pemungut
... B133: 45447 | C133: 126 | D133: ALFA Service JRK-193 Pertamina Zona#4 | F133: 354210000 | G133: IDR | H133: 1 | I133: INV021 | J133: SI Jak | K133: 45516 | L133: 347125800 | M133: 38963100 | N133: 7084200 | O133: 0 | P133: Pemungut
B134: 45539 | C134: 127 | D134: Revenue Repair Electric Assisted Stimulation Machine (no 23) | F134: 89000000 | G134: IDR | H134: 1 | I134: INV023 | J134: LBU | K134: 45553 | L134: 96920000 | M134: 9790000 | N134: 1780000 | O134: 0
B135: 45539 | C135: 128 | D135: Revenue Repair Electric Assisted Stimulation Machine (no 23) | F135: 89000000 | G135: IDR | H135: 1 | I135: INV023 | J135: LBU | K135: 45553 | L135: 96920000 | M135: 9790000 | N135: 1780000 | O135: 0
B136: 45539 | C136: 129 | D136: Revenue Repair Electric Assisted Stimulation Machine (no 23) | F136: 89000000 | G136: IDR | H136: 1 | I136: INV023 | J136: LBU | K136: 45553 | L136: 96920000 | M136: 9790000 | N136: 1780000 | O136: 0
B137: 45539 | C137: 130 | D137: Revenue Repair Electric Assisted Stimulation Machine (no 23) | F137: 89000000 | G137: IDR | H137: 1 | I137: INV023 | J137: LBU | K137: 45553 | L137: 96920000 | M137: 9790000 | N137: 1780000 | O137: 0
B138: 45539 | C138: 131 | D138: Revenue Repair Electric Assisted Stimulation Machine (no 23) | F138: 89000000 | G138: IDR | H138: 1 | I138: INV023 | J138: LBU | K138: 45553 | L138: 96920000 | M138: 9790000 | N138: 1780000 | O138: 0
B139: 45539 | C139: 132 | D139: Revenue Repair Electric Assisted Stimulation Machine (no 23) | F139: 89000000 | G139: IDR | H139: 1 | I139: INV023 | J139: LBU | K139: 45553 | L139: 96920000 | M139: 9790000 | N139: 1780000 | O139: 0
B140: 45539 | C140: 133 | D140: Revenue Repair Electric Assisted Stimulation Machine (no 23) | F140: 89000000 | G140: IDR | H140: 1 | I140: INV023 | J140: LBU | K140: 45553 | L140: 96920000 | M140: 9790000 | N140: 1780000 | O140: 0
B141: 45539 | C141: 134 | D141: Revenue Repair Electric Assisted Stimulation Machine (no 23) | F141: 89000000 | G141: IDR | H141: 1 | I141: INV023 | J141: LBU | K141: 45553 | L141: 96920000 | M141: 9790000 | N141: 1780000 | O141: 0
B142: 45539 | C142: 135 | D142: Revenue Repair Electric Assisted Stimulation Machine (no 23) | F142: 89000000 | G142: IDR | H142: 1 | I142: INV023 | J142: LBU | K142: 45553 | L142: 96920000 | M142: 9790000 | N142: 1780000 | O142: 0
B143: 45539 | C143: 136 | D143: Revenue Repair Electric Assisted Stimulation Machine (no 23) | F143: 89000000 | G143: IDR | H143: 1 | I143: INV023 | J143: LBU | K143: 45553 | L143: 96920000 | M143: 9790000 | N143: 1780000 | O143: 0
B144: 45539 | C144: 137 | D144: Revenue Repair Electric Assisted Stimulation Machine (no 23) | F144: 89000000 | G144: IDR | H144: 1 | I144: INV023 | J144: LBU | K144: 45553 | L144: 96920000 | M144: 9790000 | N144: 1780000 | O144: 0
B145: 45539 | C145: 138 | D145: Revenue Repair Electric Assisted Stimulation Machine (no 23) | F145: 89000000 | G145: IDR | H145: 1 | I145: INV023 | J145: LBU | K145: 45553 | L145: 96920000 | M145: 9790000 | N145: 1780000 | O145: 0
... B154: 45539 | C154: 147 | D154: Revenue Repair Electric Assisted Stimulation Machine (no 23) | F154: 89000000 | G154: IDR | H154: 1 | I154: INV023 | J154: LBU | K154: 45553 | L154: 96920000 | M154: 9790000 | N154: 1780000 | O154: 0
B155: 45537 | C155: 148 | D155: ALFA Service JRK-163 Pertamina Zona#4 | F155: 354210000 | G155: IDR | H155: 1 | I155: INV022 | J155: SI Jak | K155: 45575 | L155: 347125800 | M155: 38963100 | N155: 7084200 | O155: 0 | P155: Pemungut
B156: 45537 | C156: 149 | D156: ALFA Service JRK-163 Pertamina Zona#4 | F156: 354210000 | G156: IDR | H156: 1 | I156: INV022 | J156: SI Jak | K156: 45575 | L156: 347125800 | M156: 38963100 | N156: 7084200 | O156: 0 | P156: Pemungut
B157: 45537 | C157: 150 | D157: ALFA Service JRK-163 Pertamina Zona#4 | F157: 354210000 | G157: IDR | H157: 1 | I157: INV022 | J157: SI Jak | K157: 45575 | L157: 347125800 | M157: 38963100 | N157: 7084200 | O157: 0 | P157: Pemungut
B158: 45537 | C158: 151 | D158: ALFA Service JRK-163 Pertamina Zona#4 | F158: 354210000 | G158: IDR | H158: 1 | I158: INV022 | J158: SI Jak | K158: 45575 | L158: 347125800 | M158: 38963100 | N158: 7084200 | O158: 0 | P158: Pemungut
B159: 45537 | C159: 152 | D159: ALFA Service JRK-163 Pertamina Zona#4 | F159: 354210000 | G159: IDR | H159: 1 | I159: INV022 | J159: SI Jak | K159: 45575 | L159: 347125800 | M159: 38963100 | N159: 7084200 | O159: 0 | P159: Pemungut
B160: 45537 | C160: 153 | D160: ALFA Service JRK-163 Pertamina Zona#4 | F160: 354210000 | G160: IDR | H160: 1 | I160: INV022 | J160: SI Jak | K160: 45575 | L160: 347125800 | M160: 38963100 | N160: 7084200 | O160: 0 | P160: Pemungut
B161: 45537 | C161: 154 | D161: ALFA Service JRK-163 Pertamina Zona#4 | F161: 354210000 | G161: IDR | H161: 1 | I161: INV022 | J161: SI Jak | K161: 45575 | L161: 347125800 | M161: 38963100 | N161: 7084200 | O161: 0 | P161: Pemungut
B162: 45537 | C162: 155 | D162: ALFA Service JRK-163 Pertamina Zona#4 | F162: 354210000 | G162: IDR | H162: 1 | I162: INV022 | J162: SI Jak | K162: 45575 | L162: 347125800 | M162: 38963100 | N162: 7084200 | O162: 0 | P162: Pemungut
B163: 45537 | C163: 156 | D163: ALFA Service JRK-163 Pertamina Zona#4 | F163: 354210000 | G163: IDR | H163: 1 | I163: INV022 | J163: SI Jak | K163: 45575 | L163: 347125800 | M163: 38963100 | N163: 7084200 | O163: 0 | P163: Pemungut
B164: 45537 | C164: 157 | D164: ALFA Service JRK-163 Pertamina Zona#4 | F164: 354210000 | G164: IDR | H164: 1 | I164: INV022 | J164: SI Jak | K164: 45575 | L164: 347125800 | M164: 38963100 | N164: 7084200 | O164: 0 | P164: Pemungut
B165: 45537 | C165: 158 | D165: ALFA Service JRK-163 Pertamina Zona#4 | F165: 354210000 | G165: IDR | H165: 1 | I165: INV022 | J165: SI Jak | K165: 45575 | L165: 347125800 | M165: 38963100 | N165: 7084200 | O165: 0 | P165: Pemungut
B166: 45537 | C166: 159 | D166: ALFA Service JRK-163 Pertamina Zona#4 | F166: 354210000 | G166: IDR | H166: 1 | I166: INV022 | J166: SI Jak | K166: 45575 | L166: 347125800 | M166: 38963100 | N166: 7084200 | O166: 0 | P166: Pemungut
... B175: 45537 | C175: 168 | D175: ALFA Service JRK-163 Pertamina Zona#4 | F175: 354210000 | G175: IDR | H175: 1 | I175: INV022 | J175: SI Jak | K175: 45575 | L175: 347125800 | M175: 38963100 | N175: 7084200 | O175: 0 | P175: Pemungut
B176: 45576 | C176: 169 | D176: Revenue Project TIS (no 28 ) | F176: 819200000 | G176: IDR | H176: 1 | I176: INV028 | J176: Barikin Sakti | K176: 45579 | L176: 892928000 | M176: 90112000 | N176: 16384000 | O176: 0
B177: 45576 | C177: 170 | D177: Revenue Project TIS (no 28 ) | F177: 819200000 | G177: IDR | H177: 1 | I177: INV028 | J177: Barikin Sakti | K177: 45579 | L177: 892928000 | M177: 90112000 | N177: 16384000 | O177: 0
B178: 45576 | C178: 171 | D178: Revenue Project TIS (no 28 ) | F178: 819200000 | G178: IDR | H178: 1 | I178: INV028 | J178: Barikin Sakti | K178: 45579 | L178: 892928000 | M178: 90112000 | N178: 16384000 | O178: 0
B179: 45576 | C179: 172 | D179: Revenue Project TIS (no 28 ) | F179: 819200000 | G179: IDR | H179: 1 | I179: INV028 | J179: Barikin Sakti | K179: 45579 | L179: 892928000 | M179: 90112000 | N179: 16384000 | O179: 0
B180: 45576 | C180: 173 | D180: Revenue Project TIS (no 28 ) | F180: 819200000 | G180: IDR | H180: 1 | I180: INV028 | J180: Barikin Sakti | K180: 45579 | L180: 892928000 | M180: 90112000 | N180: 16384000 | O180: 0
B181: 45576 | C181: 174 | D181: Revenue Project TIS (no 28 ) | F181: 819200000 | G181: IDR | H181: 1 | I181: INV028 | J181: Barikin Sakti | K181: 45579 | L181: 892928000 | M181: 90112000 | N181: 16384000 | O181: 0
B182: 45576 | C182: 175 | D182: Revenue Project TIS (no 28 ) | F182: 819200000 | G182: IDR | H182: 1 | I182: INV028 | J182: Barikin Sakti | K182: 45579 | L182: 892928000 | M182: 90112000 | N182: 16384000 | O182: 0
B183: 45576 | C183: 176 | D183: Revenue Project TIS (no 28 ) | F183: 819200000 | G183: IDR | H183: 1 | I183: INV028 | J183: Barikin Sakti | K183: 45579 | L183: 892928000 | M183: 90112000 | N183: 16384000 | O183: 0
B184: 45576 | C184: 177 | D184: Revenue Project TIS (no 28 ) | F184: 819200000 | G184: IDR | H184: 1 | I184: INV028 | J184: Barikin Sakti | K184: 45579 | L184: 892928000 | M184: 90112000 | N184: 16384000 | O184: 0
B185: 45576 | C185: 178 | D185: Revenue Project TIS (no 28 ) | F185: 819200000 | G185: IDR | H185: 1 | I185: INV028 | J185: Barikin Sakti | K185: 45579 | L185: 892928000 | M185: 90112000 | N185: 16384000 | O185: 0
B186: 45576 | C186: 179 | D186: Revenue Project TIS (no 28 ) | F186: 819200000 | G186: IDR | H186: 1 | I186: INV028 | J186: Barikin Sakti | K186: 45579 | L186: 892928000 | M186: 90112000 | N186: 16384000 | O186: 0
B187: 45576 | C187: 180 | D187: Revenue Project TIS (no 28 ) | F187: 819200000 | G187: IDR | H187: 1 | I187: INV028 | J187: Barikin Sakti | K187: 45579 | L187: 892928000 | M187: 90112000 | N187: 16384000 | O187: 0
... B196: 45576 | C196: 189 | D196: Revenue Project TIS (no 28 ) | F196: 819200000 | G196: IDR | H196: 1 | I196: INV028 | J196: Barikin Sakti | K196: 45579 | L196: 892928000 | M196: 90112000 | N196: 16384000 | O196: 0
B197: 45572 | C197: 190 | D197: ALFA Service JRK-095 Pertamina Zona#4 | F197: 354210000 | G197: IDR | H197: 1 | I197: INV027 | J197: SI Jak | K197: 45607 | L197: 347125800 | M197: 38963100 | N197: 7084200 | O197: 0 | P197: Pemungut
B198: 45572 | C198: 191 | D198: ALFA Service JRK-095 Pertamina Zona#4 | F198: 354210000 | G198: IDR | H198: 1 | I198: INV027 | J198: SI Jak | K198: 45607 | L198: 347125800 | M198: 38963100 | N198: 7084200 | O198: 0 | P198: Pemungut
B199: 45572 | C199: 192 | D199: ALFA Service JRK-095 Pertamina Zona#4 | F199: 354210000 | G199: IDR | H199: 1 | I199: INV027 | J199: SI Jak | K199: 45607 | L199: 347125800 | M199: 38963100 | N199: 7084200 | O199: 0 | P199: Pemungut
B200: 45572 | C200: 193 | D200: ALFA Service JRK-095 Pertamina Zona#4 | F200: 354210000 | G200: IDR | H200: 1 | I200: INV027 | J200: SI Jak | K200: 45607 | L200: 347125800 | M200: 38963100 | N200: 7084200 | O200: 0 | P200: Pemungut
B201: 45572 | C201: 194 | D201: ALFA Service JRK-095 Pertamina Zona#4 | F201: 354210000 | G201: IDR | H201: 1 | I201: INV027 | J201: SI Jak | K201: 45607 | L201: 347125800 | M201: 38963100 | N201: 7084200 | O201: 0 | P201: Pemungut
B202: 45572 | C202: 195 | D202: ALFA Service JRK-095 Pertamina Zona#4 | F202: 354210000 | G202: IDR | H202: 1 | I202: INV027 | J202: SI Jak | K202: 45607 | L202: 347125800 | M202: 38963100 | N202: 7084200 | O202: 0 | P202: Pemungut
B203: 45572 | C203: 196 | D203: ALFA Service JRK-095 Pertamina Zona#4 | F203: 354210000 | G203: IDR | H203: 1 | I203: INV027 | J203: SI Jak | K203: 45607 | L203: 347125800 | M203: 38963100 | N203: 7084200 | O203: 0 | P203: Pemungut
B204: 45572 | C204: 197 | D204: ALFA Service JRK-095 Pertamina Zona#4 | F204: 354210000 | G204: IDR | H204: 1 | I204: INV027 | J204: SI Jak | K204: 45607 | L204: 347125800 | M204: 38963100 | N204: 7084200 | O204: 0 | P204: Pemungut
B205: 45572 | C205: 198 | D205: ALFA Service JRK-095 Pertamina Zona#4 | F205: 354210000 | G205: IDR | H205: 1 | I205: INV027 | J205: SI Jak | K205: 45607 | L205: 347125800 | M205: 38963100 | N205: 7084200 | O205: 0 | P205: Pemungut
B206: 45572 | C206: 199 | D206: ALFA Service JRK-095 Pertamina Zona#4 | F206: 354210000 | G206: IDR | H206: 1 | I206: INV027 | J206: SI Jak | K206: 45607 | L206: 347125800 | M206: 38963100 | N206: 7084200 | O206: 0 | P206: Pemungut
B207: 45572 | C207: 200 | D207: ALFA Service JRK-095 Pertamina Zona#4 | F207: 354210000 | G207: IDR | H207: 1 | I207: INV027 | J207: SI Jak | K207: 45607 | L207: 347125800 | M207: 38963100 | N207: 7084200 | O207: 0 | P207: Pemungut
B208: 45572 | C208: 201 | D208: ALFA Service JRK-095 Pertamina Zona#4 | F208: 354210000 | G208: IDR | H208: 1 | I208: INV027 | J208: SI Jak | K208: 45607 | L208: 347125800 | M208: 38963100 | N208: 7084200 | O208: 0 | P208: Pemungut
... B239: 45569 | C239: 232 | D239: MFC Service TGB-033 Pertamina Cirebon | F239: 280000000 | G239: IDR | H239: 1 | I239: INV025 | J239: Elnusa | K239: 45653 | L239: 412577100 | M239: 30800000 | N239: 5600000 | O239: 2900 | P239: Pemungut
B240: 45569 | C240: 233 | D240: PLT Service TGB-033 Pertamina Cirebon | F240: 141000000 | G240: IDR | H240: 1 | I240: INV026 | J240: Elnusa | K240: 45653 | L240: 0 | M240: 15510000 | N240: 2820000 | O240: 0
B241: 45569 | C241: 234 | D241: MFC Service TGB-033 Pertamina Cirebon | F241: 280000000 | G241: IDR | H241: 1 | I241: INV025 | J241: Elnusa | K241: 45653 | L241: 412577100 | M241: 30800000 | N241: 5600000 | O241: 2900 | P241: Pemungut
B242: 45569 | C242: 235 | D242: PLT Service TGB-033 Pertamina Cirebon | F242: 141000000 | G242: IDR | H242: 1 | I242: INV026 | J242: Elnusa | K242: 45653 | L242: 0 | M242: 15510000 | N242: 2820000 | O242: 0
...

Sheet Laba rugi -2024
B3: PT. EXSPAN WIRELINE INDONESIA | G3: PT. EXSPAN WIRELINE INDONESIA
B4: LABA RUGI | TAHUN 2024 | G4: NERACA |TAHUN YANG BERAKHIR, 31 DESEMBER 2024
D6: PT. Exspan Wireline Indonesia | I6: PT. Exspan Wireline Indonesia
D7: (Rp) | I7: (Rp)
B8: PENDAPATAN | G8: AKTIVA | H8: AKTIVA
C9: PENDAPATAN LANGSUNG | D9: Rp | E9: =SUM('Revenue-Cost_2024'!F8:F280) | G9: AKTIVA LANCAR | H9: AKTIVA LANCAR
C10: PENDAPATAN LAIN LAIN | D10: Rp | E10: =SUM('Revenue-Cost_2024'!F281:F301) | H10: KAS DAN SETARA KAS TAHUN SEBELUMNYA | I10: Rp | J10: 161401093
H11: KAS DAN SETARA KAS TAHUN LAPORAN | I11: Rp | J11: =ROUND(E41-'Business Summary'!E13, 0)
B12: TOTAL PENDAPATAN | D12: Rp | E12: =SUM(E9:E11) | H12: PIUTANG USAHA | I12: Rp | J12: 0
H13: PAJAK BAYAR DI MUKA (pph23) | I13: Rp | J13: 0
B14: BEBAN LANGSUNG | H14: BIAYA BAYAR DI MUKA | I14: Rp | J14: 0
C15: BIAYA SEWA PERALATAN | D15: Rp | E15: ='Revenue-Cost_2024'!I1015 | H15: PIUTANG LAIN LAIN | I15: Rp | J15: 0
C16: BIAYA RESEARCH (R&D) | D16: Rp | E16: ='Revenue-Cost_2024'!J1015 | H16: TOTAL AKTIVA LANCAR | I16: Rp | J16: =SUM(J10:J15)
C17: BIAYA INTERPRETASI LOG DATA | D17: Rp | E17: ='Revenue-Cost_2024'!K1015 | H17: ACTIVA TETAP
C18: BIAYA OPERASI | D18: Rp | E18: ='Revenue-Cost_2024'!L1015 | G18: ACTIVA TETAP
B19: TOTAL BIAYA LANGSUNG | D19: Rp | E19: =SUM(E15:E18)
H20: INVENTARIS KANTOR | I20: Rp | J20: 0
B21: BEBAN TIDAK LANGSUNG
C22: BISNIS DEV | D22: Rp | E22: ='Revenue-Cost_2024'!Q1015 | H22: TOTAL AKTIVA TETAP | I22: Rp | J22: =J20
B23: TOTAL BIAYA TIDAK LANGSUNG | D23: Rp | E23: =SUM(E22:E22)
G24: ACTIVA LAIN LAIN | H24: ACTIVA LAIN LAIN | J24: 0
B25: BIAYA ADMINISTRASI DAN UMUM | H25: TOTAL AKTIVA LAIN LAIN | I25: Rp | J25: 0
C26: ADMINISTRASI | D26: Rp | E26: ='Revenue-Cost_2024'!M1015 | H26: TOTAL AKTIVA LAIN LAIN | I26: Rp | J26: =SUM(J25:J25)
C27: PEMBELIAN BARANG | D27: Rp | E27: ='Revenue-Cost_2024'!N1015
C28: SEWA KANTOR | D28: Rp | E28: ='Revenue-Cost_2024'!O1015 | G28: TOTAL AKTIVA | H28: TOTAL AKTIVA | I28: Rp | J28: =J26+J22+J16
C29: KESEHATAN | D29: Rp | E29: ='Revenue-Cost_2024'!P1015
B30: TOTAL BIAYA ADMINISTRASI DAN UMUM | D30: Rp | E30: =SUM(E26:E29) | G30: HUTANG DAN MODAL | H30: HUTANG DAN MODAL
B32: TOTAL BIAYA | D32: Rp | E32: =E19+E23+E30 | G32: HUTANG LANCAR | H32: HUTANG LANCAR
H33: HUTANG USAHA | I33: Rp | J33: 0
B34: PENDAPATAN/BEBAN LAIN LAIN | H34: HUTANG GAJI | I34: Rp | J34: 0
C35: PENDAPATAN LAIN LAIN | D35: Rp | E35: 0 | H35: HUTANG PEMEGANG SAHAM | I35: Rp | J35: 0
H36: BIAYA YANG MASIH HARUS DI BAYAR | I36: Rp | J36: 0
B37: LABA RUGI SEBELUM PAJAK | D37: Rp | E37: =E12-E32
H38: TOTAL HUTANG LANCAR | I38: Rp | J38: =SUM(J33:J36)
B39: CORPORATE TAX (PPh 29) | D39: Rp | E39: 0
G40: MODAL | H40: MODAL
B41: LABA / RUGI BERSIH | D41: Rp | E41: =E37-E39 | H41: MODAL SAHAM | I41: Rp | J41: 0
H42: LABA DI TAHAN | I42: Rp | J42: 0
H43: TOTAL LABA (RUGI) DITAHAN | I43: Rp | J43: =J28-J38-J41-J42
H44: TOTAL MODAL | I44: Rp | J44: =SUM(J41:J43)
H46: TOTAL HUTANG DAN MODAL | I46: Rp | J46: =J44+J38
B49: Nama Lengkap | G49: Nama Lengkap
B50: Direktur | G50: Direktur

Sheet Business Summary
B3: PT. EXSPAN WIRELINE INDONESIA
B4: BUSINESS SUMMARY | TAHUN 2024
B6: # | C6: Items | D6: Amount
B7: 1 | C7: Revenue | D7: Rp | E7: =SUM('Revenue-Cost_2024'!F8:F301)
B8: 2 | C8: Revenue Diterima (Setelah Pajak) | D8: Rp | E8: =E7-SUM('Revenue-Cost_2024'!N8:N301)
B9: 3 | C9: Biaya | D9: Rp | E9: =SUM('Revenue-Cost_2024'!I1015:Q1015)
B10: 4 | C10: Profit SebelumTax | D10: Rp | E10: =E7-E9
B11: 5 | C11: PPh Badan (22%*50%) | D11: Rp | E11: =E10*22%*50%
B12: 6 | C12: PPh 23 Dipotong oleh client | D12: Rp | E12: =SUM('Revenue-Cost_2024'!N8:N301)
B13: 7 | C13: Kekurangan Bayar PPh Badan | D13: Rp | E13: =E11-E12
B14: 8 | C14: Profit After Tax | D14: Rp | E14: =E10-E13
B15: 9 | C15: Deviden Dibagi | D15: Rp | E15: =E14-E16
B16: 10 | C16: Profit Ditahan | D16: Rp | E16: 53207545
B18: DEVIDEN
B19: # | C19: Nama Lengkap | D19: Rp | E19: Amount
B20: 1 | C20: Anevril Chairulsyah | D20: Rp | E20: =IF(C20="","",ROUND($E$15/COUNTA($C$20:$C$21), 0)) | G20: Pajak 10%
B21: 2 | C21: Alan Muhadjir | D21: Rp | E21: =IF(C21="","",ROUND($E$15/COUNTA($C$20:$C$21), 0)) | G21: Pajak 10%
