Workbook

Sheet Revenue-Cost_2020
B1: Daily Report - Balance Calculation Operation Cost
B2: Project | C2: : | D2: REVENUE vs OPERATION COST Tahun 2020
B3: Date | C3: : | D3: Januari - Desember 2020
B5: REVENUE & TAX
B6: Invoice Date | C6: # | D6: Detail/Description | F6: INVOICE VALUE | G6: Currency | H6: Currency Exchange | I6: INVOICE Number | J6: Client | K6: Receive Date | L6: AMOUNT RECEIVED | M6: PPn | N6: PPH (Pasal 23) | O6: Biaya transfer | P6: Remark
L7: IDR | M7: 0.11 | N7: 0.02 | Q7: con: inc.PPN11%
D8: Belum ada data revenue dan pajak
B9: REVENUE (IDR) | F9: =SUM(F8:F8) | L9: =SUM(L8:L8) | M9: =SUM(M8:M8) | N9: =SUM(N8:N8) | O9: =SUM(O8:O8)
B24: PAJAK PENGELUARAN
B25: Date | C25: # | D25: Detail/Description | F25: Transaction Value | G25: Currency | H25: Currency Exchange | I25: PPN | K25: PPh (pasal 21) | M25: PPh (pasal 23) | O25: PPh (pasal 26)
I26: Transaction | J26: PPN | K26: Transaction | L26: PPh - 21 | M26: Transaction | N26: PPh - 23 | O26: Transaction | P26: PPh - 26
D27: Belum ada data pajak | G27: IDR | H27: 1
B28: PENERIMAAN NEGARA (TAX) (IDR) | I28: PPN | J28: =SUM(J27:J27) | K28: PPh | L28: =SUM(L27:L27) | M28: PPh | N28: =SUM(N27:N27) | O28: PPh | P28: =SUM(P27:P27) | Q28: -
B39: PENGELUARAN
B40: Date | C40: # | D40: Activity | E40: Source | F40: Jumlah | G40: Currency | H40: urrency Exchange | I40: Biaya Sewa Peralatan
D41: Belum ada data single pengeluaran
D42: OPERATION COST AND OFFICE - Expenses Report
D43: Belum ada data batch pengeluaran
B44: TOTAL | I44: 0

Sheet Laba rugi -2020
B3: PT. EXSPAN WIRELINE INDONESIA | G3: PT. EXSPAN WIRELINE INDONESIA
B4: LABA RUGI | TAHUN 2020 | G4: NERACA |TAHUN YANG BERAKHIR, 31 DESEMBER 2020
D6: PT. Exspan Wireline Indonesia | I6: PT. Exspan Wireline Indonesia
D7: (Rp) | I7: (Rp)
B8: PENDAPATAN | G8: AKTIVA | H8: AKTIVA
C9: PENDAPATAN LANGSUNG | D9: Rp | E9: 0 | G9: AKTIVA LANCAR | H9: AKTIVA LANCAR
C10: PENDAPATAN LAIN LAIN | D10: Rp | E10: 0 | H10: KAS DAN SETARA KAS TAHUN SEBELUMNYA | I10: Rp | J10: 0
H11: KAS DAN SETARA KAS TAHUN LAPORAN | I11: Rp | J11: =ROUND(E34-'Business Summary'!E13, 0)
B12: TOTAL PENDAPATAN | D12: Rp | E12: =SUM(E9:E11) | H12: PIUTANG USAHA | I12: Rp | J12: 0
H13: PAJAK BAYAR DI MUKA (pph23) | I13: Rp | J13: 0
B14: BEBAN LANGSUNG | H14: BIAYA BAYAR DI MUKA | I14: Rp | J14: 0
C15: BIAYA SEWA PERALATAN | D15: Rp | E15: ='Revenue-Cost_2020'!I44 | H15: PIUTANG LAIN LAIN | I15: Rp | J15: 0
B16: TOTAL BIAYA LANGSUNG | D16: Rp | E16: =SUM(E15:E15) | H16: TOTAL AKTIVA LANCAR | I16: Rp | J16: =SUM(J10:J15)
H17: ACTIVA TETAP
B18: BEBAN TIDAK LANGSUNG | G18: ACTIVA TETAP
D19: Rp | E19: 0
B20: TOTAL BIAYA TIDAK LANGSUNG | D20: Rp | E20: =SUM(E19:E19) | H20: INVENTARIS KANTOR | I20: Rp | J20: 0
B22: BIAYA ADMINISTRASI DAN UMUM | H22: TOTAL AKTIVA TETAP | I22: Rp | J22: =J20
B23: TOTAL BIAYA ADMINISTRASI DAN UMUM | D23: Rp | E23: =SUM(E23:E23)
G24: ACTIVA LAIN LAIN | H24: ACTIVA LAIN LAIN | J24: 0
B25: TOTAL BIAYA | D25: Rp | E25: =E16+E20+E23 | H25: TOTAL AKTIVA LAIN LAIN | I25: Rp | J25: 0
H26: TOTAL AKTIVA LAIN LAIN | I26: Rp | J26: =SUM(J25:J25)
B27: PENDAPATAN/BEBAN LAIN LAIN
C28: PENDAPATAN LAIN LAIN | D28: Rp | E28: 0 | G28: TOTAL AKTIVA | H28: TOTAL AKTIVA | I28: Rp | J28: =J26+J22+J16
B30: LABA RUGI SEBELUM PAJAK | D30: Rp | E30: =E12-E25 | G30: HUTANG DAN MODAL | H30: HUTANG DAN MODAL
B32: CORPORATE TAX (PPh 29) | D32: Rp | E32: 0 | G32: HUTANG LANCAR | H32: HUTANG LANCAR
H33: HUTANG USAHA | I33: Rp | J33: 0
B34: LABA / RUGI BERSIH | D34: Rp | E34: =E30-E32 | H34: HUTANG GAJI | I34: Rp | J34: 0
H35: HUTANG PEMEGANG SAHAM | I35: Rp | J35: 0
H36: BIAYA YANG MASIH HARUS DI BAYAR | I36: Rp | J36: 0
H38: TOTAL HUTANG LANCAR | I38: Rp | J38: =SUM(J33:J36)
H40: MODAL
H41: MODAL SAHAM | I41: Rp | J41: 0
H42: LABA DI TAHAN | I42: Rp | J42: 0
H43: TOTAL LABA (RUGI) DITAHAN | I43: Rp | J43: =J28-J38-J41-J42
H44: TOTAL MODAL | I44: Rp | J44: =SUM(J41:J43)
H46: TOTAL HUTANG DAN MODAL | I46: Rp | J46: =J44+J38
B49: Nama Lengkap | G49: Nama Lengkap
B50: Direktur | G50: Direktur

Sheet Business Summary
B3: PT. EXSPAN WIRELINE INDONESIA
B4: BUSINESS SUMMARY | TAHUN 2020
B6: # | C6: Items | D6: Amount
B7: 1 | C7: Revenue | D7: Rp | E7: =SUM('Revenue-Cost_2020'!F8:F8)
B8: 2 | C8: Revenue Diterima (Setelah Pajak) | D8: Rp | E8: =E7-SUM('Revenue-Cost_2020'!N8:N8)
B9: 3 | C9: Biaya | D9: Rp | E9: =SUM('Revenue-Cost_2020'!I44:I44)
B10: 4 | C10: Profit SebelumTax | D10: Rp | E10: =E7-E9
B11: 5 | C11: PPh Badan (22%*50%) | D11: Rp | E11: =E10*22%*50%
B12: 6 | C12: PPh 23 Dipotong oleh client | D12: Rp | E12: =SUM('Revenue-Cost_2020'!N8:N8)
B13: 7 | C13: Kekurangan Bayar PPh Badan | D13: Rp | E13: =E11-E12
B14: 8 | C14: Profit After Tax | D14: Rp | E14: =E10-E13
B15: 9 | C15: Deviden Dibagi | D15: Rp | E15: =E14-E16
B16: 10 | C16: Profit Ditahan | D16: Rp | E16: 0
B18: DEVIDEN
B19: # | C19: Nama Lengkap | D19: Rp | E19: Amount
