Workbook

Sheet Revenue-Cost_2026
B1: Daily Report - Balance Calculation Operation Cost
B2: Project | C2: : | D2: REVENUE vs OPERATION COST Tahun 2026
B3: Date | C3: : | D3: Januari - Desember 2026
B5: REVENUE & TAX
B6: Invoice Date | C6: # | D6: Detail/Description | F6: INVOICE VALUE | G6: Currency | H6: Currency Exchange | I6: INVOICE Number | J6: Client | K6: Receive Date | L6: AMOUNT RECEIVED | M6: PPn | N6: PPH (Pasal 23) | O6: Biaya transfer | P6: Remark
L7: IDR | M7: 0.11 | N7: 0.02
B8: 45302 | C8: 2 | D8: ALFA Service PDP-075 Pertamina Zona#4 | F8: 354210000 | G8: IDR | H8: 1 | I8: INV017 | J8: SI Jak | K8: 45350 | L8: 347125800 | M8: =(F8*11%) | N8: =(F8*2%) | O8: =F8-N8-L8 | P8: Pemungut
B9: 45301 | C9: 3 | D9: Revenue data procesing MTD_Tomori | F9: 150000000 | G9: IDR | H9: 1 | I9: INV015 | J9: TGE | K9: 45399 | L9: 166500000 | M9: =(F9*11%) | N9: =(F9*2%) | O9: 0 | Q9: inc.PPN11%
B10: 45302 | C10: 4 | D10: ALFA Service PDS-01ST Pertamina Zona#4 | F10: 354210000 | G10: IDR | H10: 1 | I10: INV019 | J10: SI Jak | K10: 45425 | L10: 347125800 | M10: =(F10*11%) | N10: =(F10*2%) | O10: =F10-N10-L10 | P10: Pemungut
B11: 45302 | C11: 5 | D11: ALFA Service JRK-254 Pertamina Zona#4 | F11: 354210000 | G11: IDR | H11: 1 | I11: INV018 | J11: SI Jak | K11: 45453 | L11: 347125800 | M11: =(F11*11%) | N11: =(F11*2%) | O11: =F11-N11-L11 | P11: Pemungut
B12: 45446 | C12: 6 | D12: ALFA Service TLJ-58 Pertamina Zona#4 | F12: 354210000 | G12: IDR | H12: 1 | I12: INV020 | J12: SI Jak | K12: 45497 | L12: 347125800 | M12: =(F12*11%) | N12: =(F12*2%) | O12: =F12-N12-L12 | P12: Pemungut
B13: 45447 | C13: 7 | D13: ALFA Service JRK-193 Pertamina Zona#4 | F13: 354210000 | G13: IDR | H13: 1 | I13: INV021 | J13: SI Jak | K13: 45516 | L13: 347125800 | M13: =(F13*11%) | N13: =(F13*2%) | O13: =F13-N13-L13 | P13: Pemungut
B14: 45539 | C14: 8 | D14: Revenue Repair Electric Assisted Stimulation Machine (no 23) | F14: 89000000 | G14: IDR | H14: 1 | I14: INV023 | J14: LBU | K14: 45553 | L14: =(89000000*98%)+9700000 | M14: =(F14*11%) | N14: =(F14*2%) | Q14: inc.PPN11%
B15: 45537 | C15: 9 | D15: ALFA Service JRK-163 Pertamina Zona#4 | F15: 354210000 | G15: IDR | H15: 1 | I15: INV022 | J15: SI Jak | K15: 45575 | L15: 347125800 | M15: =(F15*11%) | N15: =(F15*2%) | O15: =F15-N15-L15 | P15: Pemungut
B16: 45576 | C16: 10 | D16: Revenue Project TIS (no 28 ) | F16: 819200000 | G16: IDR | H16: 1 | I16: INV028 | J16: Barikin Sakti | K16: 45579 | L16: 892928000 | M16: =(F16*11%) | N16: =(F16*2%) | O16: =L16-(F16+M16-N16) | Q16: inc.PPN11%
B17: 45572 | C17: 11 | D17: ALFA Service JRK-095 Pertamina Zona#4 | F17: 354210000 | G17: IDR | H17: 1 | I17: INV027 | J17: SI Jak | K17: 45607 | L17: 347125800 | M17: =(F17*11%) | N17: =(F17*2%) | O17: =F17-N17-L17 | P17: Pemungut
B18: 45569 | C18: 12 | D18: ALFA Service TGB-033 Pertamina Cirebon | F18: 290000000 | G18: IDR | H18: 1 | I18: INV024 | J18: Elnusa | K18: 45646 | L18: 284197100 | M18: =(F18*11%) | N18: =(F18*2%) | O18: =F18-N18-L18 | P18: Pemungut
B19: 45569 | C19: 13 | D19: MFC Service TGB-033 Pertamina Cirebon | F19: 280000000 | G19: IDR | H19: 1 | I19: INV025 | J19: Elnusa | K19: 45653 | L19: 412577100 | M19: =(F19*11%) | N19: =(F19*2%) | O19: =F19+F20-L19-(N19+N20) | P19: Pemungut
B20: 45569 | C20: 14 | D20: PLT Service TGB-033 Pertamina Cirebon | F20: 141000000 | G20: IDR | H20: 1 | I20: INV026 | J20: Elnusa | M20: =(F20*11%) | N20: =(F20*2%) | P20: Pemungut
B21: 45657 | C21: 15 | D21: Bunga Bank 2024 | F21: 6925425 | G21: IDR | L21: =F21
B22: REVENUE (IDR) | F22: 0 | L22: =SUM(L8:L21) | M22: =SUM(M8:M21) | N22: 0
B24: PAJAK PENGELUARAN
B25: Date | C25: # | D25: Detail/Description | F25: Transaction Value | G25: Currency | H25: Currency Exchange | I25: PPN | K25: PPh (pasal 21) | M25: PPh (pasal 23) | O25: PPh (pasal 26)
I26: Transaction | J26: PPN | K26: Transaction | L26: PPh - 21 | M26: Transaction | N26: PPh - 23 | O26: Transaction | P26: PPh - 26
B27: 45289 | C27: 1 | D27: Belum ada data pajak | F27: 33836000 | G27: IDR | H27: 1 | J27: 33836000
B28: 45302 | D28: Tax PPN 11% (Project TGE MEPI Rimau Pembayaran Ke-2) | F28: 33836000 | J28: 33836000
B29: 45351 | D29: Tax PPN 11% (Project TGE MEPI Tomori) | F29: 16500000 | J29: 16500000
B30: 45567 | D30: Tax PPN 11% (Perbaikan Repair Electric Assisted Stimulation Machine) | F30: 9790000 | J30: 9790000
B31: 45546 | D31: Pinalty Telat bayar pajak PP21 Sewa tool ALFA 2023 | F31: 25439666 | L31: 25439666
B32: 45546 | D32: Tax PPN 11% pajak Inv-007 tahun 2023 sarulla project - Sibat | F32: 96126126 | J32: 97126126
B33: 45589 | D33: Penalty telat bayar pajak PPN project sarulla_INV-007_under Sibat | F33: 17716045
B34: 45593 | D34: Pemindahbukan dari double bayar (29 des 2023) utk PPN Inv-028 | F34: 33836000 | J34: 33836000
B35: 45607 | D35: Kekurangan pajak PPn Inv-028 (barikikn Sakti)(1/3 nya dari PBK pajak) | F35: 56276000 | J35: 56276000
B36: 45607 | D36: Kekurangan pajak final PPH 23 keuntungan perusahaan tahun 2023 | F36: 1726469 | N36: 1726469
B37: PENERIMAAN NEGARA (TAX) (IDR) | I37: PPN | J37: 0 | K37: PPh | L37: 0 | M37: PPh | N37: 0 | O37: PPh | P37: 0 | Q37: -
B39: PENGELUARAN
B40: Date | C40: # | D40: Activity | E40: Source | F40: Jumlah | G40: Currency | H40: urrency Exchange | I40: Biaya Research (R&D) | J40: Biaya Operasi | K40: Biaya Sewa Peralatan | L40: Biaya Interpretasi Log Data | M40: Administrasi | N40: Pembelian Barang | O40: Sewa Kantor | P40: Kesehatan | Q40: Bisnis Dev | R40: asdasd | S40: makanan jepang | T40: aaaaa | U40: bbbbb | V40: asdsad | W40: dfgdfgdfgd | X40: 12312
D41: Accommodation
B42: 46094 | C42: 1 | D42: diofavian | E42: BCA | F42: 101 | G42: IDR | H42: 1 | J42: 101
D43: asdasda
B44: 46103 | C44: 2 | D44: asdsadasdasd | E44: BCA | F44: 12312312312 | G44: IDR | H44: 1 | V44: 12312312312
D45: Biaya Bank
B46: 46103 | C46: 3 | D46: 21231 | E46: BRI | F46: 111111 | G46: IDR | H46: 1 | M46: 111111
D47: Gaji
B48: 46093 | C48: 4 | D48: Gaji mael | E48: Mandiri | F48: 234234234 | G48: IDR | H48: 1 | J48: 234234234
B49: 46093 | C49: 5 | D49: gaji diofavian | E49: BRI | F49: 300000 | G49: IDR | H49: 1 | I49: 300000
D50: Pembuatan Alat
B51: 46093 | C51: 6 | D51: sdasd | E51: BNI | F51: 50000 | G51: IDR | H51: 1 | I51: 50000
B52: 46093 | C52: 7 | D52: 12 | E52: BRI | F52: 121 | G52: IDR | H52: 1 | I52: 121
B53: 46093 | C53: 8 | D53: sfdsf | E53: BRI | F53: 234234 | G53: IDR | H53: 1 | I53: 234234
B54: 46103 | C54: 9 | D54: hari senin | E54: BRI | F54: 1112121 | G54: IDR | H54: 1 | I54: 1112121
B55: 46103 | C55: 10 | D55: werwerwerwer | E55: BCA | F55: 123123123 | G55: IDR | H55: 1 | I55: 123123123
D56: Rental Tool
B57: 46095 | C57: 11 | D57: coba maka | E57: BRI | F57: 123123123112 | G57: IDR | H57: 1 | K57: 123123123112
D58: Sewa Ruangan
B59: 46097 | C59: 12 | D59: aaaaaaaaaaaaaaaa | E59: Mandiri | F59: 1111111 | G59: IDR | H59: 1 | O59: 1111111
D60: Software License
B61: 46106 | C61: 13 | D61: jajsj | E61: BCA | F61: 13131 | G61: IDR | H61: 1 | L61: 13131
B63: TOTAL | I63: =SUM(I41:I62) | J63: =SUM(J41:J62) | K63: =SUM(K41:K62) | L63: =SUM(L41:L62) | M63: =SUM(M41:M62) | N63: =SUM(N41:N62) | O63: =SUM(O41:O62) | P63: =SUM(P41:P62) | ... X63: =SUM(X41:X62)
D97: OPERATION COST AND OFFICE - Expenses Report
B98: Expense#1 | C98: : | D98: asdasd
D99: asdasda
B100: 46100 | C100: 1 | D100: asdasda | F100: 123123123 | G100: IDR | H100: 1 | V100: 123123123
B127: Expense#2 | C127: : | D127: kerja ke goweel
D128: Biaya Bank
B129: 46093 | C129: 1 | D129: 23000 | F129: 200000 | G129: IDR | H129: 1 | M129: 200000
D130: Pembuatan Alat
B131: 46093 | C131: 2 | D131: 123123 | F131: 544000 | G131: USD | H131: 16000 | I131: 544000
B145: Expense#3 | C145: : | D145: kerja sampingan
D146: Hand Tools
B147: 46099 | C147: 1 | D147: asdasd11 | F147: 1231231 | G147: IDR | H147: 1 | N147: 1231231
B155: Expense#4 | C155: : | D155: Pengeluaran Batch
D156: nanas
B157: 46093 | C157: 1 | D157: 12312 | F157: 123123 | G157: IDR | H157: 1 | I157: 123123
D158: Pembuatan Alat
B159: 46093 | C159: 2 | D159: 123123 | F159: 12312312 | G159: IDR | H159: 1 | I159: 12312312
B164: Expense#5 | C164: : | D164: Pengeluaran Batch
D165: pepaya
B166: Expense#6 | C166: : | D166: gowel party
D167: Rental Tool
B168: 46093 | C168: 1 | D168: blejar party | F168: 12312312 | G168: IDR | H168: 1 | K168: 12312312
B185: Expense#7 | C185: :
D186: Transportation
B187: 45408 | C187: 1 | D187: Fuels | F187: 284308 | G187: IDR | H187: 1 | I187: =$H187*$F187
B188: 45410 | C188: 2 | D188: Toll | F188: 298000 | G188: IDR | H188: 1 | I188: =$H188*$F188
D189: Accommodation
B190: 45410 | C190: 3 | D190: Hotel 2 days | F190: 1357481 | G190: IDR | H190: 1 | I190: =F190
B191: 45410 | C191: 4 | D191: Laundry 2 days | F191: 100000 | G191: IDR | H191: 1 | I191: =F191
D192: Meal
B193: 45410 | C193: 6 | D193: Meals 2 days 1 Persons @ 150K IDR/day | F193: 300000 | G193: IDR | H193: 1 | I193: =F193
D194: Allowance
B195: 45410 | C195: 7 | D195: Tunjangan Lapangan for 2 days | F195: 200 | G195: USD | H195: 16257 | I195: =H195*F195
B196: Expense#8 | C196: :
D197: Transportation
B198: 45418 | C198: 1 | D198: Jakarta - Palembang - Jakarta | F198: 1387800 | G198: IDR | H198: 1 | I198: =$H198*$F198
D199: Transportation
B200: 45419 | C200: 2 | D200: Taxi + Tol to Airport Jakarta | F200: =55000+179140 | G200: IDR | H200: 1 | I200: =$H200*$F200
B201: 45419 | C201: 3 | D201: Airport park + fuel + tol Indralaya | F201: =5000+200000+27000 | G201: IDR | H201: 1 | I201: =$H201*$F201
B202: 45420 | C202: 4 | D202: Car Rental | F202: =1.5*400000 | G202: IDR | H202: 1 | I202: =$H202*$F202
B203: 45420 | C203: 5 | D203: Tol Indralaya | F203: 27000 | G203: IDR | H203: 1 | I203: =$H203*$F203
...

Sheet Laba rugi -2026
B3: PT. EXSPAN WIRELINE INDONESIA | G3: PT. EXSPAN WIRELINE INDONESIA
B4: LABA RUGI | TAHUN 2026 | G4: NERACA | TAHUN YANG BERAKHIR, 31 DESEMBER 2026 | K4: CATATAN KEAMANAN
K5: Kolom ini aman dari overwrite sistem.
D6: PT. Exspan Wireline Indonesia | I6: PT. Exspan Wireline Indonesia | K6: Diverifikasi pada: 2026-03-29 15:47
D7: (Rp) | I7: (Rp)
B8: PENDAPATAN | G8: AKTIVA
C9: PENDAPATAN LANGSUNG | D9: Rp | E9: =SUM('Revenue-Cost_2026'!F8:F20) | G9: AKTIVA LANCAR
C10: PENDAPATAN LAIN LAIN | D10: Rp | E10: =SUM('Revenue-Cost_2026'!F21) | H10: KAS DAN SETARA KAS TAHUN SEBELUMNYA | I10: Rp | J10: 0
H11: KAS DAN SETARA KAS TAHUN LAPORAN | I11: Rp | J11: =E46-'Business Summary'!E13
B12: TOTALPENDAPATAN | D12: Rp | E12: =SUM(E9:E11) | H12: PIUTANG USAHA | I12: Rp | J12: 0
H13: PAJAK BAYAR DI MUKA (pph23) | I13: Rp | J13: 0
B14: BEBAN LANGSUNG | H14: BIAYA BAYAR DI MUKA | I14: Rp | J14: 0
C15: Biaya Operasi | D15: Rp | E15: ='Revenue-Cost_2026'!I750 | H15: PIUTANG LAIN LAIN | I15: Rp | J15: 0
C16: Biaya research (R & D) | D16: Rp | E16: ='Revenue-Cost_2026'!J750 | H16: TOTAL AKTIVA LANCAR | I16: Rp | J16: =SUM(J10:J15)
C17: BIAYA SEWA PERALATAN | D17: Rp | E17: ='Revenue-Cost_2026'!K750
C18: BIAYA Data Processing | D18: Rp | E18: ='Revenue-Cost_2026'!L750 | G18: ACTIVA TETAP
H20: INVENTARIS KANTOR | I20: Rp | J20: 0
B21: TOTAL BIAYA LANGSUNG | D21: Rp | E21: =SUM(E15:E20)
H22: TOTAL AKTIVA TETAP | I22: Rp | J22: =J20
B23: BEBAN TIDAK LANGSUNG | E23: ='Revenue-Cost_2026'!Q750
G24: ACTIVA LAIN LAIN | J24: 0
D25: Rp | J25: 0
H26: TOTAL AKTIVA LAIN LAIN | I26: Rp | J26: =SUM(J25:J25)
B27: TOTAL BIAYA TIDAK LANGSUNG | D27: Rp | E27: =SUM(E22:E26)
G28: TOTAL AKTIVA | I28: Rp | J28: =J26+J22+J16
B29: BIAYA ADMINISTRASI DAN UMUM
C30: BIAYA ADMINISTRASI | D30: Rp | E30: ='Revenue-Cost_2026'!M750 | G30: HUTANG DAN MODAL
C31: BIAYA PEMBELIAN Barang | D31: Rp | E31: ='Revenue-Cost_2026'!N750
C32: BIAYA SEWA KANTOR | D32: Rp | E32: ='Revenue-Cost_2026'!O750 | G32: HUTANG LANCAR
C33: BIAYA KESEHATAN | D33: Rp | E33: ='Revenue-Cost_2026'!P750 | H33: HUTANG USAHA | I33: Rp | J33: 0
H34: HUTANG GAJI | I34: Rp | J34: 0
B35: TOTAL BIAYA ADMINISTRASI DAN UMUM | D35: Rp | E35: =SUM(E30:E34) | H35: HUTANG PEMEGANG SAHAM | I35: Rp | J35: 0
H36: BIAYA YANG MASIH HARUS DI BAYAR | I36: Rp | J36: 0
B37: TOTAL BIAYA | D37: Rp | E37: =E35+E21+E27
H38: TOTAL HUTANG LANCAR | J38: =SUM(J33:J36)
B39: PENDAPATAN/BEBAN LAIN LAIN | D39: Rp
C40: PENDAPATAN LAINNYA | D40: Rp | E40: 0 | G40: MODAL
H41: MODAL SAHAM | I41: Rp | J41: 0
B42: LABA RUGI SEBELUM PAJAK | D42: Rp | E42: =E12-E37 | H42: LABA DI TAHAN | I42: Rp | J42: 0
H43: TOTAL LABA (RUGI) DITAHAN | I43: Rp | J43: =J28-J38-J41-J42
B44: CORPORATE TAX (PPh 29) | D44: Rp | E44: 0 | H44: TOTAL MODAL | I44: Rp | J44: =SUM(J41:J43)
B46: LABA / RUGI BERSIH | E46: =E42-E44 | G46: TOTAL HUTANG DAN MODAL | I46: Rp | J46: =J44+J38
B50: Direktur | G50: Direktur

Sheet Business Summary
B3: PT. EXSPAN WIRELINE INDONESIA
B4: BUSINESS SUMMARY | TAHUN 2026
B6: # | C6: Items | D6: Amount
B7: 1 | C7: Revenue | D7: Rp | E7: ='Revenue-Cost_2026'!F22
B8: 2 | C8: Revenue Diterima (Setelah Pajak) | D8: Rp | E8: =E7-'Revenue-Cost_2026'!N22
B9: 3 | C9: Biaya | D9: Rp | E9: =SUM('Revenue-Cost_2026'!I750:Q750)
B10: 4 | C10: Profit SebelumTax | D10: Rp | E10: =E7-E9
B11: 5 | C11: PPh Badan (22%*50%) | D11: Rp | E11: =E10*22%*50%
B12: 6 | C12: PPh 23 Dipotong oleh client | D12: Rp | E12: ='Revenue-Cost_2026'!N22
B13: 7 | C13: Kekurangan Bayar PPh Badan | D13: Rp | E13: =E11-E12
B14: 8 | C14: Profit After Tax | D14: Rp | E14: =E10-E13
B15: 9 | C15: Deviden Dibagi | D15: Rp | E15: =E14-E16
B16: 10 | C16: Profit Ditahan | D16: Rp | E16: 200
B18: DEVIDEN
